Workbook

Sheet Sheet
A1: Question_id | B1: Dimension | C1: Question_text | D1: Answer_options_1 | E1: Answer_options_2 | F1: Answer_options_3 | G1: Answertype | H1: Scoring_rule | I1: Retrieval_query | J1: Evidence_expectation | K1: Weight | L1: Score numeric | M1: Selected_option | N1: Points | O1: Weighted_points | P1: Max_points | Q1: Normalized_0_5 | R1: EU_AI_ACT | S1: NIST_AI_RMF | T1: ISO_42001 | U1: AI_TRISM
A2: 1 | B2: Data Readiness | C2: Is data available and accessible for AI initiatives? | D2: Data needed for AI initiatives is scattered across systems, difficult to locate, and often requires manual extraction or individual access requests. There is no clear ownership, catalog, or standardized way to make datasets available for reuse. | E2: Key datasets for AI initiatives can be accessed, but availability depends on specific teams, projects, or technical specialists. Some documentation or data pipelines exist, yet access is not consistently standardized across the organization and reuse remains limited. | F2: Relevant data for AI initiatives is discoverable, documented, and accessible through standardized mechanisms such as data catalogs, governed pipelines, or self-service platforms. Ownership, access controls, and data provisioning processes are clearly defined to support scalable AI development. | G2: single_choice | H2: 1->1, 2->3, 3->5 | K2: 5 | L2: =IF(M2="",0,N2) -> 0 | N2: =IF(M2="", "", IF(M2=1,1,IF(M2=2,3,IF(M2=3,5,"")))) | O2: =IF(M2="", "", N2 * IF(K2="",1,K2)) | P2: =5 * IF(K2="",1,K2) -> 25 | Q2: =IF(M2="", "", (O2 / P2) * 5) | R2: YES | S2: YES | T2: YES | U2: YES
A3: 2 | B3: Data Readiness | C3: Are fairness metrics systematically evaluated when assessing AI model performance across different groups or populations? | D3: Model performance evaluation relies solely on traditional accuracy metrics, neglecting the measurement of fairness across protected groups or sub-populations. | E3: Data scientists are aware of fairness metrics and occasionally apply them, but their use is not standardized, documented, or integrated into the formal model acceptance criteria. | F3: Standardized fairness metrics (e.g., equal opportunity, demographic parity) are systematically applied, tracked, and reported as a mandatory component of the model development and deployment process. | G3: single_choice | H3: 1->1, 2->3, 3->6 | K3: 4 | L3: =IF(M3="",0,N3) -> 0 | N3: =IF(M3="", "", IF(M3=1,1,IF(M3=2,3,IF(M3=3,5,"")))) | O3: =IF(M3="", "", N3 * IF(K3="",1,K3)) | P3: =5 * IF(K3="",1,K3) -> 20 | Q3: =IF(M3="", "", (O3 / P3) * 5) | R3: YES | S3: YES | T3: YES | U3: YES
A4: 3 | B4: Data Readiness | C4: Does data coverage span across business processes? | D4: Data coverage is fragmented and limited to a small number of operational systems or departments, meaning many business processes lack sufficient data to support meaningful AI analysis or model development. | E4: Data coverage includes several key business processes, enabling some AI use cases, but important parts of the value chain remain poorly represented or require significant manual integration across systems. | F4: Data coverage spans the majority of critical business processes, with integrated datasets providing consistent, end-to-end visibility across the value chain to support scalable and reliable AI development. If you want, I can also help you standardize all answer sets so they consistently follow the same maturity pattern (which makes your assessment much stronger and easier to score). | G4: single_choice | H4: 1->1, 2->3, 3->7 | K4: 4 | L4: =IF(M4="",0,N4) -> 0 | N4: =IF(M4="", "", IF(M4=1,1,IF(M4=2,3,IF(M4=3,5,"")))) | O4: =IF(M4="", "", N4 * IF(K4="",1,K4)) | P4: =5 * IF(K4="",1,K4) -> 20 | Q4: =IF(M4="", "", (O4 / P4) * 5) | R4: YES | S4: YES | T4: YES
A5: 4 | B5: Data Readiness | C5: Is data quality complete and accurate? | D5: This is not in place; practices are ad hoc and rely on manual workarounds in isolated teams. | E5: Data quality complete and accurate exists for some key datasets or processes, but it is inconsistent across teams and not fully documented or standardized. | F5: This is implemented enterprise-wide with clear ownership, standards, and automation where possible, enabling consistent and scalable AI use. | G5: single_choice | H5: 1->1, 2->3, 3->8 | K5: 5 | L5: =IF(M5="",0,N5) -> 0 | N5: =IF(M5="", "", IF(M5=1,1,IF(M5=2,3,IF(M5=3,5,"")))) | O5: =IF(M5="", "", N5 * IF(K5="",1,K5)) | P5: =5 * IF(K5="",1,K5) -> 25 | Q5: =IF(M5="", "", (O5 / P5) * 5) | R5: YES | S5: YES | T5: YES | U5: YES
A6: 5 | B6: Data Readiness | C6: Is data consistent across systems? | D6: This is not in place; practices are ad hoc and rely on manual workarounds in isolated teams. | E6: Data consistent across systems exists for some key datasets or processes, but it is inconsistent across teams and not fully documented or standardized. | F6: This is implemented enterprise-wide with clear ownership, standards, and automation where possible, enabling consistent and scalable AI use. | G6: single_choice | H6: 1->1, 2->3, 3->9 | K6: 5 | L6: =IF(M6="",0,N6) -> 0 | N6: =IF(M6="", "", IF(M6=1,1,IF(M6=2,3,IF(M6=3,5,"")))) | O6: =IF(M6="", "", N6 * IF(K6="",1,K6)) | P6: =5 * IF(K6="",1,K6) -> 25 | Q6: =IF(M6="", "", (O6 / P6) * 5) | R6: YES | S6: YES | T6: YES
A7: 6 | B7: Data Readiness | C7: Are AI model inputs, outputs, and decisions systematically logged to ensure traceability and auditability? | D7: Model predictions and the data used to generate them are not systematically logged, making it impossible to trace an AI decision back to its input or version. | E7: Some basic logging of model inputs and outputs is implemented in production systems, but it lacks versioning and comprehensive metadata required for a full forensic analysis. | F7: A robust, comprehensive audit trail is maintained for every AI decision, meticulously logging the model version, input features, prediction, and associated confidence scores for regulatory compliance and debugging. | G7: single_choice | H7: 1->1, 2->3, 3->10 | K7: 4 | L7: =IF(M7="",0,N7) -> 0 | N7: =IF(M7="", "", IF(M7=1,1,IF(M7=2,3,IF(M7=3,5,"")))) | O7: =IF(M7="", "", N7 * IF(K7="",1,K7)) | P7: =5 * IF(K7="",1,K7) -> 20 | Q7: =IF(M7="", "", (O7 / P7) * 5) | R7: YES | S7: YES | T7: YES | U7: YES
A8: 7 | B8: Data Readiness | C8: Is data up to date and updated frequently? | D8: Data is updated infrequently or with significant delays, meaning AI models often rely on outdated information that reduces the reliability and relevance of predictions or insights. | E8: Some datasets are updated regularly and support certain AI use cases, but refresh cycles vary across systems and processes, leading to inconsistent data timeliness. | F8: Data pipelines ensure datasets are updated consistently and at the frequency required for the use case, with automated refresh mechanisms enabling near real-time or regularly scheduled updates for AI models. | G8: single_choice | H8: 1->1, 2->3, 3->11 | K8: 4 | L8: =IF(M8="",0,N8) -> 0 | N8: =IF(M8="", "", IF(M8=1,1,IF(M8=2,3,IF(M8=3,5,"")))) | O8: =IF(M8="", "", N8 * IF(K8="",1,K8)) | P8: =5 * IF(K8="",1,K8) -> 20 | Q8: =IF(M8="", "", (O8 / P8) * 5) | R8: YES | S8: YES | T8: YES
A9: 8 | B9: Data Readiness | C9: Is there a process for cleaning and enriching raw data? | D9: Activities are largely ad‑hoc and depend on individual initiative rather than defined processes. | E9: Some processes exist but implementation varies between teams and projects. | F9: Processes are clearly defined, consistently applied, and supported by governance and tooling. | G9: single_choice | H9: 1->1, 2->3, 3->12 | K9: 4 | L9: =IF(M9="",0,N9) -> 0 | N9: =IF(M9="", "", IF(M9=1,1,IF(M9=2,3,IF(M9=3,5,"")))) | O9: =IF(M9="", "", N9 * IF(K9="",1,K9)) | P9: =5 * IF(K9="",1,K9) -> 20 | Q9: =IF(M9="", "", (O9 / P9) * 5) | R9: YES | S9: YES | T9: YES
A10: 9 | B10: Data Readiness | C10: Are metadata and data lineage tracked and documented consistently? | D10: Critical context regarding data origin, transformations, and definitions is missing or scattered, leading to confusion, distrust, and inefficient data exploration by AI teams. | E10: Basic metadata (e.g., column names, descriptions) is captured in some systems, but comprehensive, automated data lineage tracing from source to model is not yet established. | F10: Comprehensive metadata and data lineage are systematically tracked and documented using automated tools, providing complete transparency into the origin and transformation history of all data assets. | G10: single_choice | H10: 1->1, 2->3, 3->13 | K10: 3 | L10: =IF(M10="",0,N10) -> 0 | N10: =IF(M10="", "", IF(M10=1,1,IF(M10=2,3,IF(M10=3,5,"")))) | O10: =IF(M10="", "", N10 * IF(K10="",1,K10)) | P10: =5 * IF(K10="",1,K10) -> 15 | Q10: =IF(M10="", "", (O10 / P10) * 5) | R10: YES | S10: YES | T10: YES | U10: YES
A11: 10 | B11: Data Readiness | C11: Are data privacy and compliance policies applied consistently? | D11: Compliance with regulations (e.g., GDPR, HIPAA) is left to individual teams, resulting in inconsistent application of masking, encryption, and access controls across data environments. | E11: Formal privacy policies are documented, and initial masking or anonymization is applied to sensitive data in central locations, but enforcement lacks full automation and enterprise-wide reach. | F11: Robust data privacy and compliance policies are consistently and automatically enforced across all data platforms, ensuring all AI projects adhere to regulatory requirements through automated controls. | G11: single_choice | H11: 1->1, 2->3, 3->14 | K11: 5 | L11: =IF(M11="",0,N11) -> 0 | N11: =IF(M11="", "", IF(M11=1,1,IF(M11=2,3,IF(M11=3,5,"")))) | O11: =IF(M11="", "", N11 * IF(K11="",1,K11)) | P11: =5 * IF(K11="",1,K11) -> 25 | Q11: =IF(M11="", "", (O11 / P11) * 5) | R11: YES | S11: YES | T11: YES | U11: YES
A12: 11 | B12: Data Readiness | C12: Are access and permissions properly managed? | D12: Data access is either overly permissive or managed through slow, manual request processes, creating significant security risks or causing major delays for AI development teams. | E12: Role-based access controls (RBAC) are defined for production systems, but their implementation for self-service AI development and sandbox environments remains inconsistent and manual. | F12: Granular, role-based access controls and permissions are properly managed and automated through centralized tools, ensuring secure, timely access for authorized users without hindering AI development velocity. | G12: single_choice | H12: 1->1, 2->3, 3->15 | K12: 4 | L12: =IF(M12="",0,N12) -> 0 | N12: =IF(M12="", "", IF(M12=1,1,IF(M12=2,3,IF(M12=3,5,"")))) | O12: =IF(M12="", "", N12 * IF(K12="",1,K12)) | P12: =5 * IF(K12="",1,K12) -> 20 | Q12: =IF(M12="", "", (O12 / P12) * 5) | R12: YES | S12: YES | T12: YES | U12: YES
A13: 12 | B13: Data Readiness | C13: Is data volume and frequency sufficient? | D13: The quantity of historical data or the frequency of new data generation is too low to effectively train robust and generalizable deep learning or time-sensitive operational AI models. | E13: Data volume is sufficient for standard machine learning, but highly specialized or large-scale deep learning initiatives still encounter constraints on historical depth or real-time velocity. | F13: Data volume and update frequency are fully sufficient to support all planned AI initiatives, enabling the training of large-scale models and near-real-time operational deployments. | G13: single_choice | H13: 1->1, 2->3, 3->16 | K13: 3 | L13: =IF(M13="",0,N13) -> 0 | N13: =IF(M13="", "", IF(M13=1,1,IF(M13=2,3,IF(M13=3,5,"")))) | O13: =IF(M13="", "", N13 * IF(K13="",1,K13)) | P13: =5 * IF(K13="",1,K13) -> 15 | Q13: =IF(M13="", "", (O13 / P13) * 5) | R13: YES | S13: YES | T13: YES
A14: 13 | B14: Data Readiness | C14: Is there adequate data retention history? | D14: Historical data is aggressively purged or archived, meaning models cannot be trained on sufficient long-term data to capture seasonality, trends, or rare events accurately. | E14: A formal data retention policy is drafted, but enforcement is inconsistent, and historical data for several key systems is below the desired period required for robust time-series modeling. | F14: Adequate data retention policies are strictly followed, ensuring sufficient historical data depth is available for robust time-series analysis, trend modeling, and long-term model monitoring. | G14: single_choice | H14: 1->1, 2->3, 3->17 | K14: 3 | L14: =IF(M14="",0,N14) -> 0 | N14: =IF(M14="", "", IF(M14=1,1,IF(M14=2,3,IF(M14=3,5,"")))) | O14: =IF(M14="", "", N14 * IF(K14="",1,K14)) | P14: =5 * IF(K14="",1,K14) -> 15 | Q14: =IF(M14="", "", (O14 / P14) * 5) | R14: YES | S14: YES | T14: YES | U14: YES
A15: 14 | B15: Data Readiness | C15: Is there noise and redundancy in the data? | D15: Data contains significant noise, duplicates, and irrelevant features that require immense pre-processing effort and actively impede AI model performance and stability. | E15: Some data quality issues are identified; basic deduplication and standard cleaning processes are being implemented as part of the initial data engineering pipelines. | F15: Data is regularly cleaned and validated; noise and redundancy are systematically identified and removed through automated feature engineering and quality control processes. | G15: single_choice | H15: 1->1, 2->3, 3->18 | K15: 3 | L15: =IF(M15="",0,N15) -> 0 | N15: =IF(M15="", "", IF(M15=1,1,IF(M15=2,3,IF(M15=3,5,"")))) | O15: =IF(M15="", "", N15 * IF(K15="",1,K15)) | P15: =5 * IF(K15="",1,K15) -> 15 | Q15: =IF(M15="", "", (O15 / P15) * 5) | R15: YES | S15: YES | T15: YES
A16: 15 | B16: Data Readiness | C16: Is the data biased or representative? | D16: The training data contains significant systemic biases (e.g., underrepresentation of specific customer segments), leading to AI models that will exhibit unfair or discriminatory outcomes. | E16: Initial data assessments have highlighted potential biases in certain features or historical outcomes, and mitigation strategies like re-sampling are being explored and piloted. | F16: The data is systematically assessed for bias and is actively managed to be statistically representative of the target population and use case, ensuring fair and equitable model outcomes. | G16: single_choice | H16: 1->1, 2->3, 3->19 | K16: 5 | L16: =IF(M16="",0,N16) -> 0 | N16: =IF(M16="", "", IF(M16=1,1,IF(M16=2,3,IF(M16=3,5,"")))) | O16: =IF(M16="", "", N16 * IF(K16="",1,K16)) | P16: =5 * IF(K16="",1,K16) -> 25 | Q16: =IF(M16="", "", (O16 / P16) * 5) | R16: YES | S16: YES | T16: YES | U16: YES
A17: 16 | B17: Data Readiness | C17: Is label quality sufficient for supervised learning? | D17: Labels for supervised learning are not available highly inconsistent, noisy, or incorrectly applied, significantly limiting the model's ability to achieve high accuracy and generalization. | E17: Labeling is primarily done by subject matter experts with some basic spot-checking, but formal quality control and inter-rater agreement processes are not yet standard practice. | F17: A high standard of label quality is maintained through rigorous review, multiple expert annotations, and formal quality control processes (e.g., inter-rater reliability) for all training data sets. | G17: single_choice | H17: 1->1, 2->3, 3->20 | K17: 4 | L17: =IF(M17="",0,N17) -> 0 | N17: =IF(M17="", "", IF(M17=1,1,IF(M17=2,3,IF(M17=3,5,"")))) | O17: =IF(M17="", "", N17 * IF(K17="",1,K17)) | P17: =5 * IF(K17="",1,K17) -> 20 | Q17: =IF(M17="", "", (O17 / P17) * 5) | S17: YES | T17: YES | U17: YES
A18: 17 | B18: Data Readiness | C18: Is there feature richness and granularity in the data? | D18: The available data is highly aggregated or lacks detailed attributes (features), preventing the AI models from capturing complex patterns or generating highly precise predictions. | E18: Core transactional data is available at a granular level, but enrichment with external or unstructured data sources to create rich features is performed only on select, high-priority projects. | F18: The data exhibits high feature richness and granularity, incorporating both core and enriched features that enable models to capture subtle, complex patterns for superior predictive power. | G18: single_choice | H18: 1->1, 2->3, 3->21 | K18: 3 | L18: =IF(M18="",0,N18) -> 0 | N18: =IF(M18="", "", IF(M18=1,1,IF(M18=2,3,IF(M18=3,5,"")))) | O18: =IF(M18="", "", N18 * IF(K18="",1,K18)) | P18: =5 * IF(K18="",1,K18) -> 15 | Q18: =IF(M18="", "", (O18 / P18) * 5) | R18: YES | S18: YES | T18: YES
A19: 18 | B19: Data Readiness | C19: Is there historical consistency in the data? | D19: Data schema, definitions, or collection methods have changed frequently over time, making older historical data incompatible or unreliable for training long-term AI models. | E19: Data conversion and harmonization are manually performed for large historical datasets when required, but there is no automated system to enforce schema consistency across time. | F19: Historical consistency is maintained through robust data versioning, schema evolution management, and standardized data collection protocols, ensuring all historical data is reliable and usable for training. | G19: single_choice | H19: 1->1, 2->3, 3->22 | K19: 3 | L19: =IF(M19="",0,N19) -> 0 | N19: =IF(M19="", "", IF(M19=1,1,IF(M19=2,3,IF(M19=3,5,"")))) | O19: =IF(M19="", "", N19 * IF(K19="",1,K19)) | P19: =5 * IF(K19="",1,K19) -> 15 | Q19: =IF(M19="", "", (O19 / P19) * 5) | R19: YES | S19: YES | T19: YES
A20: 19 | B20: Data Readiness | C20: Does the organization have data integration capability? | D20: The organization relies on point-to-point integrations and manual data transfers, making it difficult and slow to combine data from disparate sources into unified AI training datasets. | E20: An enterprise data integration tool is being implemented, and initial APIs are being developed for key systems, but full, centralized data orchestration capabilities are not yet mature. | F20: A robust, centralized data integration capability (e.g., automated ETL/ELT pipelines, service bus) is fully in place, enabling fast and reliable data orchestration for all AI projects. | G20: single_choice | H20: 1->1, 2->3, 3->23 | K20: 4 | L20: =IF(M20="",0,N20) -> 0 | N20: =IF(M20="", "", IF(M20=1,1,IF(M20=2,3,IF(M20=3,5,"")))) | O20: =IF(M20="", "", N20 * IF(K20="",1,K20)) | P20: =5 * IF(K20="",1,K20) -> 20 | Q20: =IF(M20="", "", (O20 / P20) * 5) | R20: YES | S20: YES | T20: YES
A21: 20 | B21: Data Readiness | C21: Are training, validation, and test datasets clearly separated and documented? | D21: Datasets are reused without clear separation, making evaluation unreliable. | E21: Basic separation exists but documentation is incomplete or inconsistently applied. | F21: Datasets are systematically separated, versioned, and documented to ensure reliable evaluation and reproducibility. | G21: single_choice | H21: 1->1, 2->3, 3->24 | K21: 4 | L21: =IF(M21="",0,N21) -> 0 | N21: =IF(M21="", "", IF(M21=1,1,IF(M21=2,3,IF(M21=3,5,"")))) | O21: =IF(M21="", "", N21 * IF(K21="",1,K21)) | P21: =5 * IF(K21="",1,K21) -> 20 | Q21: =IF(M21="", "", (O21 / P21) * 5) | R21: YES | S21: YES | T21: YES
A22: 21 | B22: Data Readiness | C22: Is dataset versioning implemented to reproduce model results? | D22: No dataset versioning; historical training data cannot be reconstructed. | E22: Partial versioning exists but is manual or limited to critical projects. | F22: Automated dataset versioning allows full reproducibility of training, evaluation, and deployment. | G22: single_choice | H22: 1->1, 2->3, 3->25 | K22: 3 | L22: =IF(M22="",0,N22) -> 0 | N22: =IF(M22="", "", IF(M22=1,1,IF(M22=2,3,IF(M22=3,5,"")))) | O22: =IF(M22="", "", N22 * IF(K22="",1,K22)) | P22: =5 * IF(K22="",1,K22) -> 15 | Q22: =IF(M22="", "", (O22 / P22) * 5) | R22: YES | S22: YES | T22: YES | U22: YES
A23: 22 | B23: Data Readiness | C23: Is data documentation sufficient to understand dataset origin, purpose, and limitations? | D23: Dataset origin and limitations are largely undocumented. | E23: Some documentation exists but is inconsistent across datasets. | F23: Standardized dataset documentation describes origin, purpose, bias risks, and limitations. | G23: single_choice | H23: 1->1, 2->3, 3->26 | K23: 3 | L23: =IF(M23="",0,N23) -> 0 | N23: =IF(M23="", "", IF(M23=1,1,IF(M23=2,3,IF(M23=3,5,"")))) | O23: =IF(M23="", "", N23 * IF(K23="",1,K23)) | P23: =5 * IF(K23="",1,K23) -> 15 | Q23: =IF(M23="", "", (O23 / P23) * 5) | R23: YES | S23: YES | T23: YES | U23: YES
A24: 23 | B24: Data Readiness | C24: Are evaluation datasets representative of real-world deployment conditions? | D24: Evaluation data differs significantly from real-world usage scenarios. | E24: Some effort is made to approximate real conditions but gaps remain. | F24: Evaluation datasets reflect real-world distributions, edge cases, and risk scenarios. | G24: single_choice | H24: 1->1, 2->3, 3->27 | K24: 4 | L24: =IF(M24="",0,N24) -> 0 | N24: =IF(M24="", "", IF(M24=1,1,IF(M24=2,3,IF(M24=3,5,"")))) | O24: =IF(M24="", "", N24 * IF(K24="",1,K24)) | P24: =5 * IF(K24="",1,K24) -> 20 | Q24: =IF(M24="", "", (O24 / P24) * 5) | R24: YES | S24: YES | T24: YES | U24: YES
A25: 24 | B25: Data Readiness | C25: Is feedback data captured to improve models after deployment? | D25: No structured feedback data is captured. | E25: Feedback is collected sporadically or manually. | F25: Systematic feedback loops capture outcomes, errors, and user signals for continuous improvement. | G25: single_choice | H25: 1->1, 2->3, 3->28 | K25: 4 | L25: =IF(M25="",0,N25) -> 0 | N25: =IF(M25="", "", IF(M25=1,1,IF(M25=2,3,IF(M25=3,5,"")))) | O25: =IF(M25="", "", N25 * IF(K25="",1,K25)) | P25: =5 * IF(K25="",1,K25) -> 20 | Q25: =IF(M25="", "", (O25 / P25) * 5) | R25: YES | S25: YES | T25: YES | U25: YES
A26: 25 | B26: Data Readiness | C26: Are edge cases and rare scenarios included in datasets? | D26: Edge cases are largely missing or discovered only after failures. | E26: Some edge cases are included but not systematically identified. | F26: Edge cases are proactively identified, curated, and included in datasets. | G26: single_choice | H26: 1->1, 2->3, 3->29 | K26: 2 | L26: =IF(M26="",0,N26) -> 0 | N26: =IF(M26="", "", IF(M26=1,1,IF(M26=2,3,IF(M26=3,5,"")))) | O26: =IF(M26="", "", N26 * IF(K26="",1,K26)) | P26: =5 * IF(K26="",1,K26) -> 10 | Q26: =IF(M26="", "", (O26 / P26) * 5) | R26: YES | S26: YES | T26: YES | U26: YES
A27: 26 | B27: Data Readiness | C27: Is data prepared to support explainability and audit requirements? | D27: Data structure limits explainability and traceability. | E27: Some features support explanation but coverage is incomplete. | F27: Data is structured to enable feature attribution, explainability, and audit. | G27: single_choice | H27: 1->1, 2->3, 3->30 | K27: 4 | L27: =IF(M27="",0,N27) -> 0 | N27: =IF(M27="", "", IF(M27=1,1,IF(M27=2,3,IF(M27=3,5,"")))) | O27: =IF(M27="", "", N27 * IF(K27="",1,K27)) | P27: =5 * IF(K27="",1,K27) -> 20 | Q27: =IF(M27="", "", (O27 / P27) * 5) | R27: YES | S27: YES | T27: YES | U27: YES
A28: 27 | B28: Data Readiness | C28: Is feature engineering standardized and reusable across projects? | D28: Feature creation is ad-hoc and project specific. | E28: Some reusable features exist but are not centrally managed. | F28: A standardized feature framework enables reuse and controlled evolution. | G28: single_choice | H28: 1->1, 2->3, 3->31 | K28: 3 | L28: =IF(M28="",0,N28) -> 0 | N28: =IF(M28="", "", IF(M28=1,1,IF(M28=2,3,IF(M28=3,5,"")))) | O28: =IF(M28="", "", N28 * IF(K28="",1,K28)) | P28: =5 * IF(K28="",1,K28) -> 15 | Q28: =IF(M28="", "", (O28 / P28) * 5) | S28: YES | T28: YES
A29: 28 | B29: Data Readiness | C29: Is data quality monitored automatically in pipelines? | D29: Data quality checks are manual or reactive. | E29: Basic automated checks exist for selected datasets. | F29: Automated monitoring detects anomalies, schema changes, and drift. | G29: single_choice | H29: 1->1, 2->3, 3->32 | K29: 4 | L29: =IF(M29="",0,N29) -> 0 | N29: =IF(M29="", "", IF(M29=1,1,IF(M29=2,3,IF(M29=3,5,"")))) | O29: =IF(M29="", "", N29 * IF(K29="",1,K29)) | P29: =5 * IF(K29="",1,K29) -> 20 | Q29: =IF(M29="", "", (O29 / P29) * 5) | R29: YES | S29: YES | T29: YES | U29: YES
A30: 29 | B30: Data Readiness | C30: Is data readiness validated before model development starts? | D30: Model work begins without formal readiness validation. | E30: Readiness is assessed informally or inconsistently. | F30: A formal data readiness checklist gates model development. | G30: single_choice | H30: 1->1, 2->3, 3->33 | K30: 4 | L30: =IF(M30="",0,N30) -> 0 | N30: =IF(M30="", "", IF(M30=1,1,IF(M30=2,3,IF(M30=3,5,"")))) | O30: =IF(M30="", "", N30 * IF(K30="",1,K30)) | P30: =5 * IF(K30="",1,K30) -> 20 | Q30: =IF(M30="", "", (O30 / P30) * 5) | R30: YES | S30: YES | T30: YES | U30: YES
A31: 30 | B31: Data Readiness | C31: Is external data evaluated for reliability and suitability before use? | D31: External data is used without structured validation. | E31: Basic validation is performed but not standardized. | F31: External data undergoes systematic evaluation for quality, bias, legal use, and relevance. | G31: single_choice | H31: 1->1, 2->3, 3->34 | K31: 2 | L31: =IF(M31="",0,N31) -> 0 | N31: =IF(M31="", "", IF(M31=1,1,IF(M31=2,3,IF(M31=3,5,"")))) | O31: =IF(M31="", "", N31 * IF(K31="",1,K31)) | P31: =5 * IF(K31="",1,K31) -> 10 | Q31: =IF(M31="", "", (O31 / P31) * 5) | R31: YES | S31: YES | T31: YES | U31: YES
A32: 31 | B32: Data Readiness | C32: Is synthetic or augmented data used in a controlled way? | D32: Synthetic data usage is uncontrolled or undocumented. | E32: Synthetic data is used but governance and validation are limited. | F32: Synthetic data generation and validation follow defined standards. | G32: single_choice | H32: 1->1, 2->3, 3->35 | K32: 2 | L32: =IF(M32="",0,N32) -> 0 | N32: =IF(M32="", "", IF(M32=1,1,IF(M32=2,3,IF(M32=3,5,"")))) | O32: =IF(M32="", "", N32 * IF(K32="",1,K32)) | P32: =5 * IF(K32="",1,K32) -> 10 | Q32: =IF(M32="", "", (O32 / P32) * 5) | R32: YES | S32: YES | T32: YES | U32: YES
A33: 32 | B33: Data Readiness | C33: Is dataset coverage sufficient across time, geography, and user groups? | D33: Data coverage gaps are unknown or significant. | E33: Some coverage analysis exists but is incomplete. | F33: Systematic coverage analysis ensures inclusion across segments and time periods. | G33: single_choice | H33: 1->1, 2->3, 3->36 | K33: 3 | L33: =IF(M33="",0,N33) -> 0 | N33: =IF(M33="", "", IF(M33=1,1,IF(M33=2,3,IF(M33=3,5,"")))) | O33: =IF(M33="", "", N33 * IF(K33="",1,K33)) | P33: =5 * IF(K33="",1,K33) -> 15 | Q33: =IF(M33="", "", (O33 / P33) * 5) | R33: YES | S33: YES | T33: YES
A34: 33 | B34: Data Readiness | C34: Is annotation guidance documented to ensure labeling consistency? | D34: Labeling guidelines are absent or informal. | E34: Basic guidelines exist but are inconsistently followed. | F34: Detailed annotation protocols ensure consistent labeling. | G34: single_choice | H34: 1->1, 2->3, 3->37 | K34: 2 | L34: =IF(M34="",0,N34) -> 0 | N34: =IF(M34="", "", IF(M34=1,1,IF(M34=2,3,IF(M34=3,5,"")))) | O34: =IF(M34="", "", N34 * IF(K34="",1,K34)) | P34: =5 * IF(K34="",1,K34) -> 10 | Q34: =IF(M34="", "", (O34 / P34) * 5) | R34: YES | S34: YES | T34: YES
A35: 34 | B35: Data Readiness | C35: Is data readiness evidence captured for impact assessments and regulatory review? | D35: Evidence is not stored or cannot be retrieved. | E35: Some evidence exists but is scattered. | F35: Data readiness evidence is centrally stored and reusable for regulatory reporting. | G35: single_choice | H35: 1->1, 2->3, 3->38 | K35: 3 | L35: =IF(M35="",0,N35) -> 0 | N35: =IF(M35="", "", IF(M35=1,1,IF(M35=2,3,IF(M35=3,5,"")))) | O35: =IF(M35="", "", N35 * IF(K35="",1,K35)) | P35: =5 * IF(K35="",1,K35) -> 15 | Q35: =IF(M35="", "", (O35 / P35) * 5) | R35: YES | S35: YES | T35: YES
A36: 35 | B36: Data Readiness | C36: Are data silos limiting the ability to create integrated AI datasets? | D36: Data is fragmented across silos with limited visibility and integration. | E36: Some integration exists but requires manual effort. | F36: Data is discoverable and can be integrated efficiently across domains. | G36: single_choice | H36: 1->1, 2->3, 3->39 | K36: 4 | L36: =IF(M36="",0,N36) -> 0 | N36: =IF(M36="", "", IF(M36=1,1,IF(M36=2,3,IF(M36=3,5,"")))) | O36: =IF(M36="", "", N36 * IF(K36="",1,K36)) | P36: =5 * IF(K36="",1,K36) -> 20 | Q36: =IF(M36="", "", (O36 / P36) * 5) | S36: YES | T36: YES
A37: 36 | B37: Data Readiness | C37: Is data discoverability sufficient to identify relevant datasets for AI initiatives? | D37: This is handled reactively with no standard process; issues are resolved ad hoc and lessons are not captured. | E37: This is handled through basic processes for critical systems, but practices are not consistently applied or measured. | F37: This is managed through standardized operational processes, metrics, and continuous improvement, integrated into day-to-day delivery. | G37: single_choice | H37: 1->1, 2->3, 3->40 | K37: 3 | L37: =IF(M37="",0,N37) -> 0 | N37: =IF(M37="", "", IF(M37=1,1,IF(M37=2,3,IF(M37=3,5,"")))) | O37: =IF(M37="", "", N37 * IF(K37="",1,K37)) | P37: =5 * IF(K37="",1,K37) -> 15 | Q37: =IF(M37="", "", (O37 / P37) * 5) | R37: YES | S37: YES | T37: YES
A38: 37 | B38: Data Readiness | C38: Can datasets be reliably reconstructed from storage systems? | D38: Training datasets cannot be reliably recreated. | E38: Reconstruction is possible but manual or incomplete. | F38: Datasets can be reproducibly rebuilt using automated pipelines and lineage. | G38: single_choice | H38: 1->1, 2->3, 3->41 | K38: 2 | L38: =IF(M38="",0,N38) -> 0 | N38: =IF(M38="", "", IF(M38=1,1,IF(M38=2,3,IF(M38=3,5,"")))) | O38: =IF(M38="", "", N38 * IF(K38="",1,K38)) | P38: =5 * IF(K38="",1,K38) -> 10 | Q38: =IF(M38="", "", (O38 / P38) * 5) | R38: YES | S38: YES | T38: YES | U38: YES
A39: 38 | B39: Operations, Culture & Delivery | C39: Are frontline users involved in designing AI-enabled workflows? | D39: AI is largely disconnected from day-to-day operations; pilots do not change how work gets done. | E39: AI is used in a few workflows, but adoption is uneven and often dependent on local champions. | F39: AI is embedded in key workflows with clear ownership, training, and performance monitoring; adoption is managed like a product. | G39: single_choice | H39: 1->1, 2->3, 3->42 | K39: 3 | L39: =IF(M39="",0,N39) -> 0 | N39: =IF(M39="", "", IF(M39=1,1,IF(M39=2,3,IF(M39=3,5,"")))) | O39: =IF(M39="", "", N39 * IF(K39="",1,K39)) | P39: =5 * IF(K39="",1,K39) -> 15 | Q39: =IF(M39="", "", (O39 / P39) * 5)
A40: 39 | B40: Operations, Culture & Delivery | C40: Is AI used to increase scalability and throughput of operations? | D40: AI is largely disconnected from day-to-day operations; pilots do not change how work gets done. | E40: AI is used in a few workflows, but adoption is uneven and often dependent on local champions. | F40: AI is embedded in key workflows with clear ownership, training, and performance monitoring; adoption is managed like a product. | G40: single_choice | H40: 1->1, 2->3, 3->43 | K40: 3 | L40: =IF(M40="",0,N40) -> 0 | N40: =IF(M40="", "", IF(M40=1,1,IF(M40=2,3,IF(M40=3,5,"")))) | O40: =IF(M40="", "", N40 * IF(K40="",1,K40)) | P40: =5 * IF(K40="",1,K40) -> 15 | Q40: =IF(M40="", "", (O40 / P40) * 5)
A41: 40 | B41: Operations, Culture & Delivery | C41: Are accountability and responsibilities updated for AI-supported processes? | D41: This is handled reactively with no standard process; issues are resolved ad hoc and lessons are not captured. | E41: This is handled through basic processes for critical systems, but practices are not consistently applied or measured. | F41: This is managed through standardized operational processes, metrics, and continuous improvement, integrated into day-to-day delivery. | G41: single_choice | H41: 1->1, 2->3, 3->44 | K41: 4 | L41: =IF(M41="",0,N41) -> 0 | N41: =IF(M41="", "", IF(M41=1,1,IF(M41=2,3,IF(M41=3,5,"")))) | O41: =IF(M41="", "", N41 * IF(K41="",1,K41)) | P41: =5 * IF(K41="",1,K41) -> 20 | Q41: =IF(M41="", "", (O41 / P41) * 5) | S41: YES | T41: YES | U41: YES
A42: 41 | B42: Operations, Culture & Delivery | C42: Is it explicitly documented which processes are not appropriate for AI? | D42: No criteria exist for excluding AI from processes; suitability is decided informally. | E42: Some exclusions exist, but the rationale is inconsistent and not governed. | F42: Clear suitability criteria are defined; processes not fit for AI are explicitly excluded and revisited periodically. | G42: single_choice | H42: 1->1, 2->3, 3->46 | K42: 3 | L42: =IF(M42="",0,N42) -> 0 | N42: =IF(M42="", "", IF(M42=1,1,IF(M42=2,3,IF(M42=3,5,"")))) | O42: =IF(M42="", "", N42 * IF(K42="",1,K42)) | P42: =5 * IF(K42="",1,K42) -> 15 | Q42: =IF(M42="", "", (O42 / P42) * 5) | R42: YES | S42: YES | T42: YES
A43: 42 | B43: Operations, Culture & Delivery | C43: Are fallback procedures defined for when AI fails in operations? | D43: No formal fallback procedures are defined for AI failures, meaning operational teams must respond ad hoc when systems produce incorrect outputs, become unavailable, or behave unexpectedly. | E43: Basic fallback procedures exist for some critical AI systems, such as switching to manual processes or predefined rules, but these procedures are not consistently documented, tested, or applied across all AI-driven operations. | F43: Comprehensive fallback procedures are formally defined, documented, and regularly tested for all operational AI systems, enabling automated or well-coordinated transitions to alternative processes, rule-based systems, or human oversight when failures occur. | G43: single_choice | H43: 1->1, 2->3, 3->47 | K43: 5 | L43: =IF(M43="",0,N43) -> 0 | N43: =IF(M43="", "", IF(M43=1,1,IF(M43=2,3,IF(M43=3,5,"")))) | O43: =IF(M43="", "", N43 * IF(K43="",1,K43)) | P43: =5 * IF(K43="",1,K43) -> 25 | Q43: =IF(M43="", "", (O43 / P43) * 5) | R43: YES | S43: YES | T43: YES | U43: YES
A44: 43 | B44: Operations, Culture & Delivery | C44: Is it clear who remains accountable for decisions supported by AI? | D44: Accountability for AI-supported decisions is ambiguous, leading to gaps when issues occur. | E44: Accountability is defined for some processes, but not consistently across the organization. | F44: Business owners remain accountable for outcomes; responsibilities are clearly defined end-to-end for AI-supported decisions. | G44: single_choice | H44: 1->1, 2->3, 3->48 | K44: 5 | L44: =IF(M44="",0,N44) -> 0 | N44: =IF(M44="", "", IF(M44=1,1,IF(M44=2,3,IF(M44=3,5,"")))) | O44: =IF(M44="", "", N44 * IF(K44="",1,K44)) | P44: =5 * IF(K44="",1,K44) -> 25 | Q44: =IF(M44="", "", (O44 / P44) * 5) | R44: YES | S44: YES | T44: YES | U44: YES
A45: 44 | B45: Operations, Culture & Delivery | C45: Are process outcomes compared before vs after AI implementation on an ongoing basis? | D45: This is handled reactively with no standard process; issues are resolved ad hoc and lessons are not captured. | E45: This is handled through basic processes for critical systems, but practices are not consistently applied or measured. | F45: This is managed through standardized operational processes, metrics, and continuous improvement, integrated into day-to-day delivery. | G45: single_choice | H45: 1->1, 2->3, 3->49 | K45: 3 | L45: =IF(M45="",0,N45) -> 0 | N45: =IF(M45="", "", IF(M45=1,1,IF(M45=2,3,IF(M45=3,5,"")))) | O45: =IF(M45="", "", N45 * IF(K45="",1,K45)) | P45: =5 * IF(K45="",1,K45) -> 15 | Q45: =IF(M45="", "", (O45 / P45) * 5) | S45: YES | T45: YES
A46: 45 | B46: Operations, Culture & Delivery | C46: Is a human override (human-in-the-loop) formally enforced for critical processes? | D46: Human oversight is unclear; it’s ambiguous who can override AI outputs and when. | E46: Override is possible in some cases, but rules and accountability are inconsistent. | F46: Human-in-the-loop and override are clearly designed into workflows, with roles, thresholds, and audit trails. | G46: single_choice | H46: 1->1, 2->3, 3->50 | K46: 5 | L46: =IF(M46="",0,N46) -> 0 | N46: =IF(M46="", "", IF(M46=1,1,IF(M46=2,3,IF(M46=3,5,"")))) | O46: =IF(M46="", "", N46 * IF(K46="",1,K46)) | P46: =5 * IF(K46="",1,K46) -> 25 | Q46: =IF(M46="", "", (O46 / P46) * 5) | R46: YES | S46: YES | T46: YES | U46: YES
A47: 46 | B47: Operations, Culture & Delivery | C47: Is there a culture of experimentation and rapid learning with AI? | D47: The culture is risk-averse; experimentation is discouraged and AI initiatives stall due to fear of failure. | E47: Some pockets experiment, but learning is not shared and leadership support is inconsistent. | F47: A learning culture is actively fostered; experimentation is encouraged with clear guardrails and rapid learning cycles. | G47: single_choice | H47: 1->1, 2->3, 3->51 | K47: 4 | L47: =IF(M47="",0,N47) -> 0 | N47: =IF(M47="", "", IF(M47=1,1,IF(M47=2,3,IF(M47=3,5,"")))) | O47: =IF(M47="", "", N47 * IF(K47="",1,K47)) | P47: =5 * IF(K47="",1,K47) -> 20 | Q47: =IF(M47="", "", (O47 / P47) * 5)
A48: 47 | B48: Operations, Culture & Delivery | C48: Is data/AI trusted and used to inform everyday decisions? | D48: This is handled reactively with no standard process; issues are resolved ad hoc and lessons are not captured. | E48: This is handled through basic processes for critical systems, | F48: This is managed through standardized operational processes, metrics, | G48: single_choice | H48: 1->1, 2->3, 3->52 | K48: 4 | L48: =IF(M48="",0,N48) -> 0 | N48: =IF(M48="", "", IF(M48=1,1,IF(M48=2,3,IF(M48=3,5,"")))) | O48: =IF(M48="", "", N48 * IF(K48="",1,K48)) | P48: =5 * IF(K48="",1,K48) -> 20 | Q48: =IF(M48="", "", (O48 / P48) * 5) | S48: YES | T48: YES | U48: YES
A49: 48 | B49: Operations, Culture & Delivery | C49: Is data and AI systematically used to support everyday operational decisions? | D49: Data and AI are rarely used in day-to-day decision making, and most operational decisions continue to rely primarily on manual judgement or informal analysis. | E49: Data and AI are used to support decision making in some critical processes, but adoption remains limited to specific teams or use cases. | F49: Data and AI are systematically embedded into everyday operational decision making across key business processes. | G49: single_choice | H49: 1->1, 2->3, 3->53 | K49: 4 | L49: =IF(M49="",0,N49) -> 0 | N49: =IF(M49="", "", IF(M49=1,1,IF(M49=2,3,IF(M49=3,5,"")))) | O49: =IF(M49="", "", N49 * IF(K49="",1,K49)) | P49: =5 * IF(K49="",1,K49) -> 20 | Q49: =IF(M49="", "", (O49 / P49) * 5) | S49: YES | T49: YES
A50: 49 | B50: Operations, Culture & Delivery | C50: Are fears and concerns about AI openly discussed and addressed? | D50: Resistance is unmanaged; AI is perceived as a threat and adoption is low. | E50: Concerns are acknowledged, but engagement and support are inconsistent. | F50: Concerns are actively addressed; psychological safety and transparent communication enable healthy adoption. | G50: single_choice | H50: 1->1, 2->3, 3->56 | K50: 3 | L50: =IF(M50="",0,N50) -> 0 | N50: =IF(M50="", "", IF(M50=1,1,IF(M50=2,3,IF(M50=3,5,"")))) | O50: =IF(M50="", "", N50 * IF(K50="",1,K50)) | P50: =5 * IF(K50="",1,K50) -> 15 | Q50: =IF(M50="", "", (O50 / P50) * 5)
A51: 50 | B51: Operations, Culture & Delivery | C51: Is AI perceived as augmentation rather than a threat to people? | D51: This is handled reactively with no standard process; issues are resolved ad hoc and lessons are not captured. | E51: This is handled through basic processes for critical systems, but practices are not consistently applied or measured. | F51: This is managed through standardized operational processes, metrics, and continuous improvement, integrated into day-to-day delivery. | G51: single_choice | H51: 1->1, 2->3, 3->57 | K51: 3 | L51: =IF(M51="",0,N51) -> 0 | N51: =IF(M51="", "", IF(M51=1,1,IF(M51=2,3,IF(M51=3,5,"")))) | O51: =IF(M51="", "", N51 * IF(K51="",1,K51)) | P51: =5 * IF(K51="",1,K51) -> 15 | Q51: =IF(M51="", "", (O51 / P51) * 5) | U51: YES
A52: 51 | B52: Operations, Culture & Delivery | C52: Is cross-functional collaboration the norm for AI initiatives? | D52: AI initiatives are typically developed within isolated teams such as data science or IT, with limited involvement from business stakeholders or other relevant functions. | E52: Some AI initiatives involve collaboration between business, data, and technology teams, but this cooperation depends on individual projects and is not consistently established across the organization. | F52: Cross-functional collaboration between business, data, technology, and governance teams is standard practice for AI initiatives, ensuring that solutions are aligned with operational needs, technical feasibility, and organizational objectives. | G52: single_choice | H52: 1->1, 2->3, 3->58 | K52: 4 | L52: =IF(M52="",0,N52) -> 0 | N52: =IF(M52="", "", IF(M52=1,1,IF(M52=2,3,IF(M52=3,5,"")))) | O52: =IF(M52="", "", N52 * IF(K52="",1,K52)) | P52: =5 * IF(K52="",1,K52) -> 20 | Q52: =IF(M52="", "", (O52 / P52) * 5) | S52: YES | T52: YES
A53: 52 | B53: Operations, Culture & Delivery | C53: Are AI successes and learnings made visible across the organization? | D53: This is handled reactively with no standard process | E53: This is handled through basic processes | F53: This is managed through standardized operational processes | G53: single_choice | H53: 1->1, 2->3, 3->59 | K53: 3 | L53: =IF(M53="",0,N53) -> 0 | N53: =IF(M53="", "", IF(M53=1,1,IF(M53=2,3,IF(M53=3,5,"")))) | O53: =IF(M53="", "", N53 * IF(K53="",1,K53)) | P53: =5 * IF(K53="",1,K53) -> 15 | Q53: =IF(M53="", "", (O53 / P53) * 5)
A54: 53 | B54: Operations, Culture & Delivery | C54: Are roles, responsibilities, and collaboration processes clearly defined for AI initiatives? | D54: Roles and responsibilities for AI initiatives are unclear, and collaboration between teams is largely informal. | E54: Basic roles and collaboration processes are defined for some AI initiatives, but they are not consistently applied across the organization. | F54: Roles, responsibilities, and collaboration processes for AI initiatives are clearly defined and consistently applied across the organization. | G54: single_choice | H54: 1->1, 2->3, 3->60 | K54: 4 | L54: =IF(M54="",0,N54) -> 0 | N54: =IF(M54="", "", IF(M54=1,1,IF(M54=2,3,IF(M54=3,5,"")))) | O54: =IF(M54="", "", N54 * IF(K54="",1,K54)) | P54: =5 * IF(K54="",1,K54) -> 20 | Q54: =IF(M54="", "", (O54 / P54) * 5) | S54: YES | T54: YES
A55: 54 | B55: Operations, Culture & Delivery | C55: Is the effectiveness of AI initiatives monitored and continuously improved? | D55: The effectiveness of AI initiatives is rarely measured, and improvements are made only when issues arise. | E55: Some metrics exist to evaluate AI initiatives, but measurement and improvement remain inconsistent. | F55: Clear metrics are used to evaluate AI initiatives, and insights are systematically used to improve processes and outcomes. | G55: single_choice | H55: 1->1, 2->3, 3->61 | K55: 4 | L55: =IF(M55="",0,N55) -> 0 | N55: =IF(M55="", "", IF(M55=1,1,IF(M55=2,3,IF(M55=3,5,"")))) | O55: =IF(M55="", "", N55 * IF(K55="",1,K55)) | P55: =5 * IF(K55="",1,K55) -> 20 | Q55: =IF(M55="", "", (O55 / P55) * 5) | S55: YES | T55: YES
A56: 55 | B56: Operations, Culture & Delivery | C56: Is there openness about AI limitations and mistakes (no 'black box' mystique)? | D56: AI limitations and mistakes are handled reactively with no standard process; issues are resolved ad hoc and lessons are not captured. | E56: AI limitations and mistakes are handled through basic processes for critical systems, but practices are not consistently applied or measured. | F56: AI limitations and mistakes is managed through standardized operational processes, metrics, and continuous improvement, integrated into day-to-day delivery. | G56: single_choice | H56: 1->1, 2->3, 3->62 | K56: 3 | L56: =IF(M56="",0,N56) -> 0 | N56: =IF(M56="", "", IF(M56=1,1,IF(M56=2,3,IF(M56=3,5,"")))) | O56: =IF(M56="", "", N56 * IF(K56="",1,K56)) | P56: =5 * IF(K56="",1,K56) -> 15 | Q56: =IF(M56="", "", (O56 / P56) * 5) | S56: YES | U56: YES
A57: 56 | B57: Operations, Culture & Delivery | C57: Is change management applied consistently for AI adoption? | D57: No structured change approach exists; communication and training are late and inconsistent. | E57: Basic change activities exist for some initiatives, but are not repeatable. | F57: A mature change capability supports AI rollouts (stakeholder mapping, training, comms, measurement) across the portfolio. | G57: single_choice | H57: 1->1, 2->3, 3->63 | K57: 4 | L57: =IF(M57="",0,N57) -> 0 | N57: =IF(M57="", "", IF(M57=1,1,IF(M57=2,3,IF(M57=3,5,"")))) | O57: =IF(M57="", "", N57 * IF(K57="",1,K57)) | P57: =5 * IF(K57="",1,K57) -> 20 | Q57: =IF(M57="", "", (O57 / P57) * 5) | S57: YES | T57: YES
A58: 57 | B58: Operations, Culture & Delivery | C58: Is AI linked to meaningful work and purpose (not only efficiency)? | D58: AI is framed purely as efficiency; broader purpose and impacts are not discussed. | E58: Purpose is occasionally mentioned, but not operationalized. | F58: AI is linked to purpose and societal impact where relevant, strengthening legitimacy and engagement. | G58: single_choice | H58: 1->1, 2->3, 3->64 | K58: 2 | L58: =IF(M58="",0,N58) -> 0 | N58: =IF(M58="", "", IF(M58=1,1,IF(M58=2,3,IF(M58=3,5,"")))) | O58: =IF(M58="", "", N58 * IF(K58="",1,K58)) | P58: =5 * IF(K58="",1,K58) -> 10 | Q58: =IF(M58="", "", (O58 / P58) * 5)
A59: 58 | B59: Operations, Culture & Delivery | C59: Is it acceptable for employees to challenge AI-supported decisions and escalate concerns? | D59: People do not feel safe to challenge AI outputs or decisions. | E59: Some teams challenge AI outputs informally, but without consistent norms or processes. | F59: Challenging AI outputs is normalized; escalation and feedback loops are part of the operating model. | G59: single_choice | H59: 1->1, 2->3, 3->65 | K59: 4 | L59: =IF(M59="",0,N59) -> 0 | N59: =IF(M59="", "", IF(M59=1,1,IF(M59=2,3,IF(M59=3,5,"")))) | O59: =IF(M59="", "", N59 * IF(K59="",1,K59)) | P59: =5 * IF(K59="",1,K59) -> 20 | Q59: =IF(M59="", "", (O59 / P59) * 5) | R59: YES | S59: YES | T59: YES | U59: YES
A60: 59 | B60: Operations, Culture & Delivery | C60: Are sentiments and resistance signals systematically measured (surveys, pulse checks)? | D60: This is handled reactively with no standard process; issues are resolved ad hoc and lessons are not captured. | E60: This is handled through basic processes for critical systems, but practices are not consistently applied or measured. | F60: This is managed through standardized operational processes, metrics, and continuous improvement, integrated into day-to-day delivery. | G60: single_choice | H60: 1->1, 2->3, 3->66 | K60: 3 | L60: =IF(M60="",0,N60) -> 0 | N60: =IF(M60="", "", IF(M60=1,1,IF(M60=2,3,IF(M60=3,5,"")))) | O60: =IF(M60="", "", N60 * IF(K60="",1,K60)) | P60: =5 * IF(K60="",1,K60) -> 15 | Q60: =IF(M60="", "", (O60 / P60) * 5) | S60: YES | T60: YES
A61: 60 | B61: Operations, Culture & Delivery | C61: Is psychological safety explicitly fostered around AI mistakes and incidents? | D61: This is handled reactively with no standard process; issues are resolved ad hoc and lessons are not captured. | E61: This is handled through basic processes for critical systems, but practices are not consistently applied or measured. | F61: This is managed through standardized operational processes, metrics, and continuous improvement, integrated into day-to-day delivery. | G61: single_choice | H61: 1->1, 2->3, 3->67 | K61: 3 | L61: =IF(M61="",0,N61) -> 0 | N61: =IF(M61="", "", IF(M61=1,1,IF(M61=2,3,IF(M61=3,5,"")))) | O61: =IF(M61="", "", N61 * IF(K61="",1,K61)) | P61: =5 * IF(K61="",1,K61) -> 15 | Q61: =IF(M61="", "", (O61 / P61) * 5) | R61: YES | S61: YES | T61: YES | U61: YES
A62: 61 | B62: Operations, Culture & Delivery | C62: Is decision quality (not only speed/efficiency) used as a success criterion for AI? | D62: Success is measured mainly in speed/efficiency, not decision quality or outcomes. | E62: Some quality metrics exist, but are not systematically used. | F62: Decision quality and outcomes are explicitly measured and improved using AI, alongside efficiency. | G62: single_choice | H62: 1->1, 2->3, 3->68 | K62: 3 | L62: =IF(M62="",0,N62) -> 0 | N62: =IF(M62="", "", IF(M62=1,1,IF(M62=2,3,IF(M62=3,5,"")))) | O62: =IF(M62="", "", N62 * IF(K62="",1,K62)) | P62: =5 * IF(K62="",1,K62) -> 15 | Q62: =IF(M62="", "", (O62 / P62) * 5) | S62: YES | T62: YES
A63: 62 | B63: Operations, Culture & Delivery | C63: Is AI explicitly connected to societal/ethical impact in internal narratives and communications? | D63: AI is framed purely as efficiency; broader purpose and impacts are not discussed. | E63: Purpose is occasionally mentioned, but not operationalized. | F63: AI is linked to purpose and societal impact where relevant, strengthening legitimacy and engagement. | G63: single_choice | H63: 1->1, 2->3, 3->69 | K63: 2 | L63: =IF(M63="",0,N63) -> 0 | N63: =IF(M63="", "", IF(M63=1,1,IF(M63=2,3,IF(M63=3,5,"")))) | O63: =IF(M63="", "", N63 * IF(K63="",1,K63)) | P63: =5 * IF(K63="",1,K63) -> 10 | Q63: =IF(M63="", "", (O63 / P63) * 5) | S63: YES | U63: YES
A64: 63 | B64: Operations, Culture & Delivery | C64: Is AI organized centrally, decentrally, or as a hybrid model with clear rationale? | D64: AI is organized inconsistently; teams duplicate work and standards are unclear. | E64: A hybrid setup is emerging, but roles, interfaces, and standards are still developing. | F64: A clear operating model exists (platform + domain teams), with defined decision rights, reuse, and collaboration mechanisms. | G64: single_choice | H64: 1->1, 2->3, 3->70 | K64: 3 | L64: =IF(M64="",0,N64) -> 0 | N64: =IF(M64="", "", IF(M64=1,1,IF(M64=2,3,IF(M64=3,5,"")))) | O64: =IF(M64="", "", N64 * IF(K64="",1,K64)) | P64: =5 * IF(K64="",1,K64) -> 15 | Q64: =IF(M64="", "", (O64 / P64) * 5)
A65: 64 | B65: Operations, Culture & Delivery | C65: Is there effective alignment between business and IT on AI delivery? | D65: Functions work in silos; legal/risk engagement happens late. | E65: Cross-functional collaboration exists for some initiatives, but is not standard. | F65: Cross-functional collaboration is standard with early involvement of legal/risk/security in delivery and governance. | G65: single_choice | H65: 1->1, 2->3, 3->71 | K65: 5 | L65: =IF(M65="",0,N65) -> 0 | N65: =IF(M65="", "", IF(M65=1,1,IF(M65=2,3,IF(M65=3,5,"")))) | O65: =IF(M65="", "", N65 * IF(K65="",1,K65)) | P65: =5 * IF(K65="",1,K65) -> 25 | Q65: =IF(M65="", "", (O65 / P65) * 5)
A66: 65 | B66: Operations, Culture & Delivery | C66: Are AI solutions and components reused across teams? | D66: Reuse is low; solutions are built repeatedly from scratch. | E66: Some reuse exists informally, but without incentives or standard components. | F66: Reuse is designed-in via shared components, standards, and a platform team; adoption is measured. | G66: single_choice | H66: 1->1, 2->3, 3->72 | K66: 3 | L66: =IF(M66="",0,N66) -> 0 | N66: =IF(M66="", "", IF(M66=1,1,IF(M66=2,3,IF(M66=3,5,"")))) | O66: =IF(M66="", "", N66 * IF(K66="",1,K66)) | P66: =5 * IF(K66="",1,K66) -> 15 | Q66: =IF(M66="", "", (O66 / P66) * 5)
A67: 66 | B67: Operations, Culture & Delivery | C67: Are AI initiatives run as products (persistent teams) rather than one-off projects? | D67: AI is delivered as one-off projects with no post-launch ownership. | E67: Some product-like ownership exists, but funding and team stability are inconsistent. | F67: AI is operated as products with stable cross-functional teams owning outcomes end-to-end beyond go-live. | G67: single_choice | H67: 1->1, 2->3, 3->73 | K67: 4 | L67: =IF(M67="",0,N67) -> 0 | N67: =IF(M67="", "", IF(M67=1,1,IF(M67=2,3,IF(M67=3,5,"")))) | O67: =IF(M67="", "", N67 * IF(K67="",1,K67)) | P67: =5 * IF(K67="",1,K67) -> 20 | Q67: =IF(M67="", "", (O67 / P67) * 5)
A68: 67 | B68: Operations, Culture & Delivery | C68: Are decision rights and escalation paths for AI clear across functions? | D68: Decision rights are unclear; approvals and escalations are inconsistent. | E68: Some RACI exists, but not consistently followed. | F68: Decision rights, RACI, and escalation paths are clear and followed, enabling fast and safe delivery. | G68: single_choice | H68: 1->1, 2->3, 3->74 | K68: 4 | L68: =IF(M68="",0,N68) -> 0 | N68: =IF(M68="", "", IF(M68=1,1,IF(M68=2,3,IF(M68=3,5,"")))) | O68: =IF(M68="", "", N68 * IF(K68="",1,K68)) | P68: =5 * IF(K68="",1,K68) -> 20 | Q68: =IF(M68="", "", (O68 / P68) * 5) | S68: YES | T68: YES | U68: YES
A69: 68 | B69: Operations, Culture & Delivery | C69: Is cross-functional collaboration (legal, risk, IT, business) structurally embedded? | D69: Functions work in silos; legal/risk engagement happens late. | E69: This is not standard. | F69: Cross-functional collaboration is standard with early involvement of legal/risk/security in delivery and governance. | G69: single_choice | H69: 1->1, 2->3, 3->75 | K69: 5 | L69: =IF(M69="",0,N69) -> 0 | N69: =IF(M69="", "", IF(M69=1,1,IF(M69=2,3,IF(M69=3,5,"")))) | O69: =IF(M69="", "", N69 * IF(K69="",1,K69)) | P69: =5 * IF(K69="",1,K69) -> 25 | Q69: =IF(M69="", "", (O69 / P69) * 5) | R69: YES | S69: YES | T69: YES | U69: YES
A70: 69 | B70: Operations, Culture & Delivery | C70: Are responsibilities and RACI for AI delivery defined? | D70: Decision rights are unclear; approvals and escalations are inconsistent. | E70: Some RACI exists, but not consistently followed. | F70: Decision rights, RACI, and escalation paths are clear and followed, enabling fast and safe delivery. | G70: single_choice | H70: 1->1, 2->3, 3->76 | K70: 4 | L70: =IF(M70="",0,N70) -> 0 | N70: =IF(M70="", "", IF(M70=1,1,IF(M70=2,3,IF(M70=3,5,"")))) | O70: =IF(M70="", "", N70 * IF(K70="",1,K70)) | P70: =5 * IF(K70="",1,K70) -> 20 | Q70: =IF(M70="", "", (O70 / P70) * 5) | S70: YES | T70: YES
A71: 70 | B71: Operations, Culture & Delivery | C71: Do AI teams have sufficient mandate and access to data/platform resources? | D71: Ai teams do not have sufficient mandate and access to data/platform | E71: This is handled through basic processes for critical systems, but practices are not consistently applied or measured. | F71: This is managed through standardized operational processes, metrics, and continuous improvement, integrated into day-to-day delivery. | G71: single_choice | H71: 1->1, 2->3, 3->77 | K71: 4 | L71: =IF(M71="",0,N71) -> 0 | N71: =IF(M71="", "", IF(M71=1,1,IF(M71=2,3,IF(M71=3,5,"")))) | O71: =IF(M71="", "", N71 * IF(K71="",1,K71)) | P71: =5 * IF(K71="",1,K71) -> 20 | Q71: =IF(M71="", "", (O71 / P71) * 5)
A72: 71 | B72: Operations, Culture & Delivery | C72: Is it defined which AI decisions are centralized vs decentralized (by risk/value)? | D72: AI is organized inconsistently; teams duplicate work and standards are unclear. | E72: A hybrid setup is emerging, but roles, interfaces, and standards are still developing. | F72: A clear operating model exists (platform + domain teams), with defined decision rights, reuse, and collaboration mechanisms. | G72: single_choice | H72: 1->1, 2->3, 3->78 | K72: 3 | L72: =IF(M72="",0,N72) -> 0 | N72: =IF(M72="", "", IF(M72=1,1,IF(M72=2,3,IF(M72=3,5,"")))) | O72: =IF(M72="", "", N72 * IF(K72="",1,K72)) | P72: =5 * IF(K72="",1,K72) -> 15 | Q72: =IF(M72="", "", (O72 / P72) * 5) | R72: YES | S72: YES | T72: YES | U72: YES
A73: 72 | B73: Operations, Culture & Delivery | C73: Is reuse of models/patterns governed (standards, catalogs, APIs) rather than ad hoc? | D73: Reuse is low; solutions are built repeatedly from scratch. | E73: Some reuse exists informally, but without incentives or standard components. | F73: Reuse is designed-in via shared components, standards, and a platform team; adoption is measured. | G73: single_choice | H73: 1->1, 2->3, 3->79 | K73: 3 | L73: =IF(M73="",0,N73) -> 0 | N73: =IF(M73="", "", IF(M73=1,1,IF(M73=2,3,IF(M73=3,5,"")))) | O73: =IF(M73="", "", N73 * IF(K73="",1,K73)) | P73: =5 * IF(K73="",1,K73) -> 15 | Q73: =IF(M73="", "", (O73 / P73) * 5) | R73: YES | S73: YES | T73: YES
A74: 73 | B74: Operations, Culture & Delivery | C74: Is collaboration between Legal, Risk, IT and Business formalized (cadence, forums, SLAs)? | D74: Functions work in silos; legal/risk engagement happens late. | E74: Cross-functional collaboration exists for some initiatives, but is not standard. | F74: Cross-functional collaboration is standard with early involvement of legal/risk/security in delivery and governance. | G74: single_choice | H74: 1->1, 2->3, 3->80 | K74: 3 | L74: =IF(M74="",0,N74) -> 0 | N74: =IF(M74="", "", IF(M74=1,1,IF(M74=2,3,IF(M74=3,5,"")))) | O74: =IF(M74="", "", N74 * IF(K74="",1,K74)) | P74: =5 * IF(K74="",1,K74) -> 15 | Q74: =IF(M74="", "", (O74 / P74) * 5) | R74: YES | S74: YES | T74: YES | U74: YES
A75: 74 | B75: Operations, Culture & Delivery | C75: Are AI experiments designed and executed systematically (hypotheses, metrics, learnings)? | D75: Experiments are ad hoc with unclear hypotheses and little learning capture. | E75: Some experiments follow structure, but methods and documentation vary. | F75: Experimentation is systematic (hypotheses, measures, learnings), feeding a repeatable pipeline from idea to scale. | G75: single_choice | H75: 1->1, 2->3, 3->81 | K75: 4 | L75: =IF(M75="",0,N75) -> 0 | N75: =IF(M75="", "", IF(M75=1,1,IF(M75=2,3,IF(M75=3,5,"")))) | O75: =IF(M75="", "", N75 * IF(K75="",1,K75)) | P75: =5 * IF(K75="",1,K75) -> 20 | Q75: =IF(M75="", "", (O75 / P75) * 5) | S75: YES
A76: 75 | B76: Operations, Culture & Delivery | C76: Are learnings from AI initiatives documented and shared across the organization? | D76: Learnings are not captured; teams repeat mistakes. | E76: Some learnings are shared informally, but not searchable or reusable. | F76: Learnings are captured and shared in a structured, searchable way, informing standards and future work. | G76: single_choice | H76: 1->1, 2->3, 3->82 | K76: 3 | L76: =IF(M76="",0,N76) -> 0 | N76: =IF(M76="", "", IF(M76=1,1,IF(M76=2,3,IF(M76=3,5,"")))) | O76: =IF(M76="", "", N76 * IF(K76="",1,K76)) | P76: =5 * IF(K76="",1,K76) -> 15 | Q76: =IF(M76="", "", (O76 / P76) * 5)
A77: 76 | B77: Operations, Culture & Delivery | C77: Is there a clear pipeline from idea to pilot to scale (stage gates or equivalents)? | D77: Experiments are ad hoc with unclear hypotheses and little learning capture. | E77: Some experiments follow structure, but methods and documentation vary. | F77: Experimentation is systematic (hypotheses, measures, learnings), feeding a repeatable pipeline from idea to scale. | G77: single_choice | H77: 1->1, 2->3, 3->83 | K77: 4 | L77: =IF(M77="",0,N77) -> 0 | N77: =IF(M77="", "", IF(M77=1,1,IF(M77=2,3,IF(M77=3,5,"")))) | O77: =IF(M77="", "", N77 * IF(K77="",1,K77)) | P77: =5 * IF(K77="",1,K77) -> 20 | Q77: =IF(M77="", "", (O77 / P77) * 5) | S77: YES | T77: YES
A78: 77 | B78: Operations, Culture & Delivery | C78: Is there dedicated budget/time for exploration and discovery work? | D78: Exploration and exploitation are mixed, leading to confusion and poor resource allocation. | E78: Some distinction exists, but governance and funding are not fully aligned. | F78: Exploration vs exploitation are explicitly separated with tailored governance, metrics, and funding models. | G78: single_choice | H78: 1->1, 2->3, 3->84 | K78: 3 | L78: =IF(M78="",0,N78) -> 0 | N78: =IF(M78="", "", IF(M78=1,1,IF(M78=2,3,IF(M78=3,5,"")))) | O78: =IF(M78="", "", N78 * IF(K78="",1,K78)) | P78: =5 * IF(K78="",1,K78) -> 15 | Q78: =IF(M78="", "", (O78 / P78) * 5) | T78: YES
A79: 78 | B79: Operations, Culture & Delivery | C79: Does the organization collaborate with external AI partners when beneficial? | D79: The organization works mostly in isolation; partnerships are opportunistic and not aligned to AI needs. | E79: Some partnerships exist, but they are project-based and not systematically managed. | F79: A deliberate ecosystem strategy exists with partners (vendors, startups, academia) aligned to capability building and differentiation. | G79: single_choice | H79: 1->1, 2->3, 3->85 | K79: 2 | L79: =IF(M79="",0,N79) -> 0 | N79: =IF(M79="", "", IF(M79=1,1,IF(M79=2,3,IF(M79=3,5,"")))) | O79: =IF(M79="", "", N79 * IF(K79="",1,K79)) | P79: =5 * IF(K79="",1,K79) -> 10 | Q79: =IF(M79="", "", (O79 / P79) * 5)
A80: 79 | B80: Operations, Culture & Delivery | C80: Are there mechanisms for continuous monitoring of AI models? | D80: Models are deployed and left unattended, with no automated processes to detect model drift, data quality degradation, or concept drift in the production environment. | E80: Basic technical monitoring (e.g., latency, uptime) is implemented, but specific checks for model performance degradation or data drift are not yet automated or systematic. | F80: Robust, automated mechanisms for continuous monitoring are in place, actively tracking model performance, data quality, and drift in production, with alerts and automated retraining triggers established. | G80: single_choice | H80: 1->1, 2->3, 3->86 | K80: 5 | L80: =IF(M80="",0,N80) -> 0 | N80: =IF(M80="", "", IF(M80=1,1,IF(M80=2,3,IF(M80=3,5,"")))) | O80: =IF(M80="", "", N80 * IF(K80="",1,K80)) | P80: =5 * IF(K80="",1,K80) -> 25 | Q80: =IF(M80="", "", (O80 / P80) * 5) | R80: YES | S80: YES | T80: YES | U80: YES
A81: 80 | B81: Operations, Culture & Delivery | C81: Is there a clear policy on what AI knowledge can be shared vs must be protected (IP)? | D81: There is no policy on sharing vs protecting AI knowledge; risk of leakage or missed collaboration is high. | E81: Some practices exist, but are inconsistent. | F81: Clear policies balance knowledge sharing and IP protection, enabling collaboration while safeguarding competitive assets. | G81: single_choice | H81: 1->1, 2->3, 3->87 | K81: 3 | L81: =IF(M81="",0,N81) -> 0 | N81: =IF(M81="", "", IF(M81=1,1,IF(M81=2,3,IF(M81=3,5,"")))) | O81: =IF(M81="", "", N81 * IF(K81="",1,K81)) | P81: =5 * IF(K81="",1,K81) -> 15 | Q81: =IF(M81="", "", (O81 / P81) * 5) | S81: YES | T81: YES
A82: 81 | B82: Operations, Culture & Delivery | C82: Are contractual exit options and data portability ensured with AI suppliers? | D82: Contracts lack AI-specific protections; exit, portability, and audit rights are missing. | E82: Some protections exist, but are inconsistent and not tested. | F82: Contracts include AI-specific clauses (portability, audit, data rights, SLAs) and exit plans are feasible and periodically reviewed. | G82: single_choice | H82: 1->1, 2->3, 3->88 | K82: 3 | L82: =IF(M82="",0,N82) -> 0 | N82: =IF(M82="", "", IF(M82=1,1,IF(M82=2,3,IF(M82=3,5,"")))) | O82: =IF(M82="", "", N82 * IF(K82="",1,K82)) | P82: =5 * IF(K82="",1,K82) -> 15 | Q82: =IF(M82="", "", (O82 / P82) * 5) | R82: YES | S82: YES | T82: YES | U82: YES
A83: 82 | B83: Operations, Culture & Delivery | C83: Is participation in sector standards/initiatives considered to shape and anticipate AI requirements? | D83: The organization does not engage in sector standards or initiatives; it lags behind emerging norms. | E83: Some engagement exists, but it is limited and not strategic. | F83: The organization participates strategically in sector/standards initiatives to shape and anticipate requirements. | G83: single_choice | H83: 1->1, 2->3, 3->89 | K83: 2 | L83: =IF(M83="",0,N83) -> 0 | N83: =IF(M83="", "", IF(M83=1,1,IF(M83=2,3,IF(M83=3,5,"")))) | O83: =IF(M83="", "", N83 * IF(K83="",1,K83)) | P83: =5 * IF(K83="",1,K83) -> 10 | Q83: =IF(M83="", "", (O83 / P83) * 5) | S83: YES | T83: YES
A84: 83 | B84: Operations, Culture & Delivery | C84: Does the organization have the agility to adopt AI? | D84: Rigid organizational silos, slow decision-making, and bureaucratic approval processes heavily impede the initiation and deployment of AI projects. | E84: Cross-functional project teams are being piloted, and some initial steps are being taken to streamline procurement and governance for pilot projects. | F84: The organization operates with high structural and operational agility, utilizing flexible funding, empowered teams, and rapid decision cycles to quickly adopt and scale AI solutions. | G84: single_choice | H84: 1->1, 2->3, 3->90 | K84: 4 | L84: =IF(M84="",0,N84) -> 0 | N84: =IF(M84="", "", IF(M84=1,1,IF(M84=2,3,IF(M84=3,5,"")))) | O84: =IF(M84="", "", N84 * IF(K84="",1,K84)) | P84: =5 * IF(K84="",1,K84) -> 20 | Q84: =IF(M84="", "", (O84 / P84) * 5)
A85: 84 | B85: Operations, Culture & Delivery | C85: Does the organization have an AI incident reporting process? | D85: No formal process. | E85: Basic process exists. | F85: Formal incident reporting integrated with IT processes. | G85: single_choice | H85: 1->1, 2->3, 3->91 | K85: 5 | L85: =IF(M85="",0,N85) -> 0 | N85: =IF(M85="", "", IF(M85=1,1,IF(M85=2,3,IF(M85=3,5,"")))) | O85: =IF(M85="", "", N85 * IF(K85="",1,K85)) | P85: =5 * IF(K85="",1,K85) -> 25 | Q85: =IF(M85="", "", (O85 / P85) * 5) | R85: YES | S85: YES | T85: YES | U85: YES
A86: 85 | B86: Operations, Culture & Delivery | C86: Are mitigation playbooks defined for AI risks (rollback, fallback, escalation)? | D86: No playbooks. | E86: Basic playbooks exist. | F86: Playbooks are defined and tested. | G86: single_choice | H86: 1->1, 2->3, 3->92 | K86: 5 | L86: =IF(M86="",0,N86) -> 0 | N86: =IF(M86="", "", IF(M86=1,1,IF(M86=2,3,IF(M86=3,5,"")))) | O86: =IF(M86="", "", N86 * IF(K86="",1,K86)) | P86: =5 * IF(K86="",1,K86) -> 25 | Q86: =IF(M86="", "", (O86 / P86) * 5) | R86: YES | S86: YES | T86: YES | U86: YES
A87: 86 | B87: Operations, Culture & Delivery | C87: Is there a defined incident response process for AI system failures? | D87: There is no formal process to respond to AI incidents or failures. | E87: Basic response procedures exist but are not consistently applied. | F87: A defined AI incident response process exists and is used to manage failures and risks. | G87: single_choice | H87: 1->1, 2->3, 3->93 | K87: 5 | L87: =IF(M87="",0,N87) -> 0 | N87: =IF(M87="", "", IF(M87=1,1,IF(M87=2,3,IF(M87=3,5,"")))) | O87: =IF(M87="", "", N87 * IF(K87="",1,K87)) | P87: =5 * IF(K87="",1,K87) -> 25 | Q87: =IF(M87="", "", (O87 / P87) * 5) | R87: YES | S87: YES | T87: YES | U87: YES
A88: 87 | B88: Operations, Culture & Delivery | C88: Are AI successes and learnings made visible across the organization? | D88: AI outcomes and lessons learned remain within individual teams, projects, or presentations and are not consistently communicated across the organization. | E88: Selected teams share AI results and lessons through occasional updates or communities, but visibility is uneven and reuse is limited. | F88: AI successes, failures, and lessons learned are systematically communicated through structured channels, making insights visible and reusable across the organization. | G88: single_choice | H88: 1->1, 2->3, 3->94 | K88: 3 | L88: =IF(M88="",0,N88) -> 0 | N88: =IF(M88="", "", IF(M88=1,1,IF(M88=2,3,IF(M88=3,5,"")))) | O88: =IF(M88="", "", N88 * IF(K88="",1,K88)) | P88: =5 * IF(K88="",1,K88) -> 15 | Q88: =IF(M88="", "", (O88 / P88) * 5)
A89: 88 | B89: Operations, Culture & Delivery | C89: Are roles, responsibilities, and collaboration processes clearly defined for AI initiatives? | D89: Ownership for AI work is unclear and collaboration depends largely on informal coordination between teams and individuals. | E89: Core roles and collaboration arrangements are defined for some initiatives, but they are not applied consistently across all AI work. | F89: Roles, responsibilities, and cross-functional collaboration processes are clearly defined, understood, and consistently applied across AI initiatives. | G89: single_choice | H89: 1->1, 2->3, 3->95 | K89: 4 | L89: =IF(M89="",0,N89) -> 0 | N89: =IF(M89="", "", IF(M89=1,1,IF(M89=2,3,IF(M89=3,5,"")))) | O89: =IF(M89="", "", N89 * IF(K89="",1,K89)) | P89: =5 * IF(K89="",1,K89) -> 20 | Q89: =IF(M89="", "", (O89 / P89) * 5) | S89: YES | T89: YES
A90: 89 | B90: Operations, Culture & Delivery | C90: Is the effectiveness of AI initiatives monitored and continuously improved? | D90: AI initiatives are rarely tracked against clear objectives, so improvement happens mainly in response to issues or stakeholder concerns. | E90: Some initiatives are reviewed against performance or adoption metrics, but follow-up actions are inconsistent and not embedded in a continuous improvement cycle. | F90: AI initiatives are monitored against defined success measures, and the resulting insights are systematically used to improve outcomes, processes, and adoption. | G90: single_choice | H90: 1->1, 2->3, 3->96 | K90: 4 | L90: =IF(M90="",0,N90) -> 0 | N90: =IF(M90="", "", IF(M90=1,1,IF(M90=2,3,IF(M90=3,5,"")))) | O90: =IF(M90="", "", N90 * IF(K90="",1,K90)) | P90: =5 * IF(K90="",1,K90) -> 20 | Q90: =IF(M90="", "", (O90 / P90) * 5) | S90: YES | T90: YES
A91: 90 | B91: Operations, Culture & Delivery | C91: Are AI product teams funded as durable capabilities rather than temporary project budgets? | D91: AI teams rely mainly on temporary project or pilot funding, which interrupts continuity, ownership, and capability building. | E91: Some AI capacity has recurring support, but much of the work still depends on short-term approvals or case-by-case funding decisions. | F91: AI product teams are funded as enduring capabilities with stable ownership, recurring budgets, and room for ongoing development and operations. | G91: single_choice | H91: 1->1, 2->3, 3->97 | K91: 3 | L91: =IF(M91="",0,N91) -> 0 | N91: =IF(M91="", "", IF(M91=1,1,IF(M91=2,3,IF(M91=3,5,"")))) | O91: =IF(M91="", "", N91 * IF(K91="",1,K91)) | P91: =5 * IF(K91="",1,K91) -> 15 | Q91: =IF(M91="", "", (O91 / P91) * 5) | T91: YES
A92: 91 | B92: Operations, Culture & Delivery | C92: Are escalation mechanisms across domains formalized for disputes and high-risk decisions? | D92: Escalation of cross-domain disputes or high-risk AI decisions happens informally, with unclear triggers and decision rights. | E92: Escalation routes exist for certain situations, but thresholds, timelines, and ownership are not consistently defined across functions. | F92: Formal escalation mechanisms define when issues must be raised, who decides, and how cross-domain disputes and high-risk decisions are resolved. | G92: single_choice | H92: 1->1, 2->3, 3->98 | K92: 3 | L92: =IF(M92="",0,N92) -> 0 | N92: =IF(M92="", "", IF(M92=1,1,IF(M92=2,3,IF(M92=3,5,"")))) | O92: =IF(M92="", "", N92 * IF(K92="",1,K92)) | P92: =5 * IF(K92="",1,K92) -> 15 | Q92: =IF(M92="", "", (O92 / P92) * 5) | R92: YES | S92: YES | T92: YES | U92: YES
A93: 92 | B93: Operations, Culture & Delivery | C93: Is AI used to accelerate innovation cycles (time-to-insight, time-to-decision)? | D93: AI has not materially shortened the path from insight to decision, and most innovation cycles still depend on manual analysis and coordination. | E93: AI speeds up selected parts of the innovation process, but the gains are limited to certain teams or use cases and are not measured consistently. | F93: AI is deliberately used to accelerate insight generation and decision-making, with measurable improvements in innovation speed across relevant processes. | G93: single_choice | H93: 1->1, 2->3, 3->99 | K93: 3 | L93: =IF(M93="",0,N93) -> 0 | N93: =IF(M93="", "", IF(M93=1,1,IF(M93=2,3,IF(M93=3,5,"")))) | O93: =IF(M93="", "", N93 * IF(K93="",1,K93)) | P93: =5 * IF(K93="",1,K93) -> 15 | Q93: =IF(M93="", "", (O93 / P93) * 5) | S93: YES | T93: YES
A94: 93 | B94: Operations, Culture & Delivery | C94: Is it defined when to stop experimenting and commit, or stop? | D94: Experiments continue or stop without agreed criteria, making it hard to decide when to scale, pivot, commit, or end an initiative. | E94: Some projects use decision criteria or stage gates, but they are not applied consistently and choices still depend heavily on individual judgment. | F94: Clear criteria define when experiments should be scaled, committed, revised, or stopped, enabling disciplined portfolio decisions. | G94: single_choice | H94: 1->1, 2->3, 3->100 | K94: 3 | L94: =IF(M94="",0,N94) -> 0 | N94: =IF(M94="", "", IF(M94=1,1,IF(M94=2,3,IF(M94=3,5,"")))) | O94: =IF(M94="", "", N94 * IF(K94="",1,K94)) | P94: =5 * IF(K94="",1,K94) -> 15 | Q94: =IF(M94="", "", (O94 / P94) * 5)
A95: 94 | B95: Operations, Culture & Delivery | C95: Are lessons learned stored in a searchable knowledge base or pattern library? | D95: Lessons learned are stored in scattered files, meeting notes, or personal knowledge and are difficult for others to find or reuse. | E95: Some lessons are documented in shared folders or team spaces, but the information is incomplete, inconsistently tagged, and not easy to search. | F95: Lessons learned are captured in a searchable knowledge base or pattern library, making proven approaches and common pitfalls easy to reuse. | G95: single_choice | H95: 1->1, 2->3, 3->101 | K95: 2 | L95: =IF(M95="",0,N95) -> 0 | N95: =IF(M95="", "", IF(M95=1,1,IF(M95=2,3,IF(M95=3,5,"")))) | O95: =IF(M95="", "", N95 * IF(K95="",1,K95)) | P95: =5 * IF(K95="",1,K95) -> 10 | Q95: =IF(M95="", "", (O95 / P95) * 5) | S95: YES | T95: YES
A96: 95 | B96: Operations, Culture & Delivery | C96: Does governance accelerate safe learning, or does it systematically slow innovation (measured)? | D96: The effect of governance on learning speed and safe experimentation is not measured, and governance is often experienced as a source of delay. | E96: Governance practices are being adjusted to support experimentation, but evidence on whether they improve both speed and safety is still limited. | F96: Governance is designed and measured to enable safe learning, balancing control with pace and showing how it supports effective innovation. | G96: single_choice | H96: 1->1, 2->3, 3->102 | K96: 3 | L96: =IF(M96="",0,N96) -> 0 | N96: =IF(M96="", "", IF(M96=1,1,IF(M96=2,3,IF(M96=3,5,"")))) | O96: =IF(M96="", "", N96 * IF(K96="",1,K96)) | P96: =5 * IF(K96="",1,K96) -> 15 | Q96: =IF(M96="", "", (O96 / P96) * 5) | S96: YES | T96: YES
A97: 96 | B97: Operations, Culture & Delivery | C97: Are vendor dependencies and supply-chain risks understood for AI components? | D97: Key dependencies on external AI suppliers are not fully documented, leaving concentration, continuity, and resilience risks poorly understood. | E97: Important vendors and dependencies are identified for some solutions, but assessment of supply-chain and dependency risk is incomplete or inconsistent. | F97: Vendor dependencies and supply-chain risks for AI components are systematically mapped, assessed, and monitored as part of ongoing governance. | G97: single_choice | H97: 1->1, 2->3, 3->103 | K97: 4 | L97: =IF(M97="",0,N97) -> 0 | N97: =IF(M97="", "", IF(M97=1,1,IF(M97=2,3,IF(M97=3,5,"")))) | O97: =IF(M97="", "", N97 * IF(K97="",1,K97)) | P97: =5 * IF(K97="",1,K97) -> 20 | Q97: =IF(M97="", "", (O97 / P97) * 5) | R97: YES | S97: YES | T97: YES | U97: YES
A98: 97 | B98: Operations, Culture & Delivery | C98: Is AI used as a differentiator in products/services and market positioning? | D98: AI is not yet used in a meaningful way to differentiate offerings or strengthen the organization's market position. | E98: AI contributes to differentiation in selected products, services, or messages, but it is not yet a clear and consistent element of market positioning. | F98: AI is deliberately embedded in products, services, and value propositions, and it clearly strengthens competitive differentiation and positioning. | G98: single_choice | H98: 1->1, 2->3, 3->104 | K98: 3 | L98: =IF(M98="",0,N98) -> 0 | N98: =IF(M98="", "", IF(M98=1,1,IF(M98=2,3,IF(M98=3,5,"")))) | O98: =IF(M98="", "", N98 * IF(K98="",1,K98)) | P98: =5 * IF(K98="",1,K98) -> 15 | Q98: =IF(M98="", "", (O98 / P98) * 5)
A99: 98 | B99: Operations, Culture & Delivery | C99: Is AI explicitly used in employer branding and recruitment narratives? | D99: AI hardly features in employer branding or recruitment, so the organization does little to signal its ambitions or capabilities in this area. | E99: AI is mentioned in some hiring campaigns or recruitment materials, but the story is fragmented and not yet part of a broader talent proposition. | F99: AI is explicitly reflected in employer branding and recruitment narratives, helping attract talent by showing ambition, capability, and responsible use. | G99: single_choice | H99: 1->1, 2->3, 3->105 | K99: 2 | L99: =IF(M99="",0,N99) -> 0 | N99: =IF(M99="", "", IF(M99=1,1,IF(M99=2,3,IF(M99=3,5,"")))) | O99: =IF(M99="", "", N99 * IF(K99="",1,K99)) | P99: =5 * IF(K99="",1,K99) -> 10 | Q99: =IF(M99="", "", (O99 / P99) * 5)
A100: 99 | B100: Operations, Culture & Delivery | C100: Is AI reputational risk assessed for customer-facing use cases and communications? | D100: Customer-facing AI use cases and communications are launched without a structured assessment of potential reputational impact. | E100: Reputational considerations are reviewed for some visible AI use cases, but the depth and consistency of the assessment vary. | F100: Reputational risk is systematically assessed for customer-facing AI use cases and communications before launch and as part of ongoing oversight. | G100: single_choice | H100: 1->1, 2->3, 3->106 | K100: 4 | L100: =IF(M100="",0,N100) -> 0 | N100: =IF(M100="", "", IF(M100=1,1,IF(M100=2,3,IF(M100=3,5,"")))) | O100: =IF(M100="", "", N100 * IF(K100="",1,K100)) | P100: =5 * IF(K100="",1,K100) -> 20 | Q100: =IF(M100="", "", (O100 / P100) * 5) | R100: YES | S100: YES | U100: YES
...

Sheet Config
A1: Setting | B1: Value
A2: Tier_1_Name | B2: Emerging | D2: De organisatie erkent het potentieel van AI, maar heeft nog geen formele adoptie of strategie. Er is sprake van nieuwsgierigheid zonder praktische uitvoering.
A3: Tier_1_MinPct | B3: 0
A4: Tier_1_MaxPct | B4: 34.9
A5: Tier_2_Name | B5: Developing | D5: Er wordt op afdelingsniveau geëxperimenteerd met pilotprojecten. Teams gebruiken informeel tools zoals Jupyter notebooks voor eerste modellen.
A6: Tier_2_MinPct | B6: 35
A7: Tier_2_MaxPct | B7: 59.9
A8: Tier_3_Name | B8: Accelerating | D8: AI-modellen zijn geïntegreerd in specifieke bedrijfsprocessen met meetbare resultaten. Er is een team van machine learning engineers en een basis MLOps-infrastructuur aanwezig.
A9: Tier_3_MinPct | B9: 60
A10: Tier_3_MaxPct | B10: 79.9
A11: Tier_4_Name | B11: Leading | D11: AI is organisatiebreed ingebed en afgestemd op de bedrijfsstrategie. Er is een centrale governance, vaste budgetten en een focus op schaalbaarheid en compliance.
A12: Tier_4_MinPct | B12: 80
A13: Tier_4_MaxPct | B13: 100

Sheet Dimension_Summary
A1: Dimension | B1: Number_of_questions | C1: Sum_Weighted_points | D1: Sum_Max_points | E1: Dimension_Score_0_5 | F1: Dimension_Score_0_100
A2: Data Readiness | B2: =COUNTIF(Sheet!$B$2:$B$266,A2) -> 37 | C2: =SUMIF(Sheet!$B$2:$B$266,A2,Sheet!$O$2:$O$266) -> 0 | D2: =SUMIF(Sheet!$B$2:$B$266,A2,Sheet!$P$2:$P$266) -> 655 | E2: =IF(D2=0,"", ROUND((C2/D2)*5, 2)) -> 0 | F2: =IF(D2=0,"", ROUND((C2/D2)*100, 1)) -> 0
A3: Operations, Culture & Delivery | B3: =COUNTIF(Sheet!$B$2:$B$266,A3) -> 64 | C3: =SUMIF(Sheet!$B$2:$B$266,A3,Sheet!$O$2:$O$266) -> 0 | D3: =SUMIF(Sheet!$B$2:$B$266,A3,Sheet!$P$2:$P$266) -> 1120 | E3: =IF(D3=0,"", ROUND((C3/D3)*5, 2)) -> 0 | F3: =IF(D3=0,"", ROUND((C3/D3)*100, 1)) -> 0
A4: Risk, Compliance & Responsible AI | B4: =COUNTIF(Sheet!$B$2:$B$266,A4) -> 25 | C4: =SUMIF(Sheet!$B$2:$B$266,A4,Sheet!$O$2:$O$266) -> 0 | D4: =SUMIF(Sheet!$B$2:$B$266,A4,Sheet!$P$2:$P$266) -> 555 | E4: =IF(D4=0,"", ROUND((C4/D4)*5, 2)) -> 0 | F4: =IF(D4=0,"", ROUND((C4/D4)*100, 1)) -> 0
A5: Skills & Organizational Capability | B5: =COUNTIF(Sheet!$B$2:$B$266,A5) -> 33 | C5: =SUMIF(Sheet!$B$2:$B$266,A5,Sheet!$O$2:$O$266) -> 0 | D5: =SUMIF(Sheet!$B$2:$B$266,A5,Sheet!$P$2:$P$266) -> 585 | E5: =IF(D5=0,"", ROUND((C5/D5)*5, 2)) -> 0 | F5: =IF(D5=0,"", ROUND((C5/D5)*100, 1)) -> 0
A6: Strategic & Leadership Readiness | B6: =COUNTIF(Sheet!$B$2:$B$266,A6) -> 38 | C6: =SUMIF(Sheet!$B$2:$B$266,A6,Sheet!$O$2:$O$266) -> 0 | D6: =SUMIF(Sheet!$B$2:$B$266,A6,Sheet!$P$2:$P$266) -> 755 | E6: =IF(D6=0,"", ROUND((C6/D6)*5, 2)) -> 0 | F6: =IF(D6=0,"", ROUND((C6/D6)*100, 1)) -> 0
A7: Technology Infrastructure & Tooling | B7: =COUNTIF(Sheet!$B$2:$B$266,A7) -> 41 | C7: =SUMIF(Sheet!$B$2:$B$266,A7,Sheet!$O$2:$O$266) -> 0 | D7: =SUMIF(Sheet!$B$2:$B$266,A7,Sheet!$P$2:$P$266) -> 815 | E7: =IF(D7=0,"", ROUND((C7/D7)*5, 2)) -> 0 | F7: =IF(D7=0,"", ROUND((C7/D7)*100, 1)) -> 0
A8: Use Case Maturity & Adoption | B8: =COUNTIF(Sheet!$B$2:$B$266,A8) -> 27 | C8: =SUMIF(Sheet!$B$2:$B$266,A8,Sheet!$O$2:$O$266) -> 0 | D8: =SUMIF(Sheet!$B$2:$B$266,A8,Sheet!$P$2:$P$266) -> 540 | E8: =IF(D8=0,"", ROUND((C8/D8)*5, 2)) -> 0 | F8: =IF(D8=0,"", ROUND((C8/D8)*100, 1)) -> 0

Sheet Radar_Data
A1: Dimension | B1: Score_0_5 | C1: Score_0_100
A2: =Dimension_Summary!A2 -> Data Readiness | B2: =Dimension_Summary!E2 -> 0 | C2: =Dimension_Summary!F2 -> 0
A3: =Dimension_Summary!A3 -> Operations, Culture & Delivery | B3: =Dimension_Summary!E3 -> 0 | C3: =Dimension_Summary!F3 -> 0
A4: =Dimension_Summary!A4 -> Risk, Compliance & Responsible AI | B4: =Dimension_Summary!E4 -> 0 | C4: =Dimension_Summary!F4 -> 0
A5: =Dimension_Summary!A5 -> Skills & Organizational Capability | B5: =Dimension_Summary!E5 -> 0 | C5: =Dimension_Summary!F5 -> 0
A6: =Dimension_Summary!A6 -> Strategic & Leadership Readiness | B6: =Dimension_Summary!E6 -> 0 | C6: =Dimension_Summary!F6 -> 0
A7: =Dimension_Summary!A7 -> Technology Infrastructure & Tooling | B7: =Dimension_Summary!E7 -> 0 | C7: =Dimension_Summary!F7 -> 0
A8: =Dimension_Summary!A8 -> Use Case Maturity & Adoption | B8: =Dimension_Summary!E8 -> 0 | C8: =Dimension_Summary!F8 -> 0

Sheet Overall_Summary
A1: Metric | B1: Value
A2: Overall_Sum_Weighted_points | B2: =SUMPRODUCT((Sheet!$M$2:$M$266<>"")*IFERROR(Sheet!$O$2:$O$266,0)) -> #VALUE!
A3: Overall_Sum_Max_points | B3: =SUMPRODUCT((Sheet!$M$2:$M$266<>"")*Sheet!$P$2:$P$266) -> 0
A4: Overall_Score_0_5 | B4: =IF(B3=0,"", ROUND((B2/B3)*5, 2))
A5: Overall_Score_0_100 | B5: =IF(B3=0,"", ROUND((B2/B3)*100, 1))
A6: Maturity_Tier | B6: =IF(B5="","",IF(B5<=Config!B4,Config!B2,IF(B5<=Config!B7,Config!B5,IF(B5<=Config!B10,Config!B8,Config!B11))))
A7: Questions_answered | B7: =COUNTIF(Sheet!$M$2:$M$266,"<>"&"") -> 0
A8: Questions_total | B8: =COUNTA(Sheet!$A$2:$A$266) -> 265
A9: Completion_pct | B9: =IF(B8=0,"",ROUND(B7/B8*100,1)) -> 0

Sheet Column_Explanation
A1: Column | B1: Purpose | C1: Explanation | D1: Example
A2: Question_id | B2: Unique identifier | C2: Unique number used to reference and track each question in the assessment. | D2: 10, 11, 12
A3: Dimension | B3: Assessment domain | C3: Groups questions into domains such as Data Readiness, Governance, Technology, etc. Used for radar charts and maturity scoring per domain. | D3: Data Readiness
A4: Question_text | B4: Assessment question | C4: The actual question used to evaluate the organization’s AI maturity. | D4: Is data available and accessible for AI initiatives?
A5: Answer_options_1 | B5: Low maturity answer | C5: Represents the lowest maturity level (early stage / ad‑hoc practices). | D5: Data is scattered across systems
A6: Answer_options_2 | B6: Medium maturity answer | C6: Represents a developing or partially structured maturity level. | D6: Some datasets accessible but not standardized
A7: Answer_options_3 | B7: High maturity answer | C7: Represents the most advanced maturity level with structured processes. | D7: Data is governed and fully accessible
A8: Answer_type | B8: Question format | C8: Defines how the question should be answered (e.g. single choice). | D8: single_choice
A9: Required_docs | B9: Evidence guidance | C9: Lists documents that could demonstrate proof for the answer. | D9: AI Governance Policy
A10: Requires_evidence_boolean | B10: Evidence requirement flag | C10: Indicates whether documentation evidence is required to support the answer. | D10: TRUE / FALSE
A11: Retrieval_query | B11: AI document search query | C11: Query used by an AI system to search documentation repositories to find evidence. | D11: Find documentation describing AI governance policy
A12: Evidence_expectation | B12: Expected evidence description | C12: Defines what type of document or proof should be found. | D12: Documented AI governance framework
... A26: Maturity_Area | B26: Analysis grouping | C26: High‑level grouping used for reporting and analysis across maturity areas. | D26: Governance

Sheet Results_Dashboard
A1: AI Maturity Dashboard — Straightable Innovation & Strategy
A3: TOTAALSCORE | C3: VOLTOOIING ASSESSMENT
A4: Score (0–5) | B4: =Overall_Summary!B4 | C4: Vragen beantwoord | D4: =Overall_Summary!B7 -> 0 | E4: =Overall_Summary!B8&" vragen totaal" -> 265 vragen totaal
A5: Score (0–100%) | B5: =Overall_Summary!B5 | C5: Voltooiingspercentage | D5: =Overall_Summary!B9 -> 0
A6: Maturiteitsniveau | B6: =Overall_Summary!B6
A8: SCORES PER DIMENSIE
A9: Dimensie | B9: Score (0–5) | C9: Score (%) | D9: Max mogelijke score | E9: Maturiteitsniveau
A10: =Dimension_Summary!A2 -> Data Readiness | B10: =Dimension_Summary!E2 -> 0 | C10: =Dimension_Summary!F2 -> 0 | D10: =Dimension_Summary!D2 -> 655 | E10: =IF(Dimension_Summary!F2="","",IF(Dimension_Summary!F2<=Config!B4,Config!B2,IF(Dimension_Summary!F2<=Config!B7,Config!B5,IF(Dimension_Summary!F2<=Config!B10,Config!B8,Config!B11)))) -> Emerging
A11: =Dimension_Summary!A3 -> Operations, Culture & Delivery | B11: =Dimension_Summary!E3 -> 0 | C11: =Dimension_Summary!F3 -> 0 | D11: =Dimension_Summary!D3 -> 1120 | E11: =IF(Dimension_Summary!F3="","",IF(Dimension_Summary!F3<=Config!B4,Config!B2,IF(Dimension_Summary!F3<=Config!B7,Config!B5,IF(Dimension_Summary!F3<=Config!B10,Config!B8,Config!B11)))) -> Emerging
A12: =Dimension_Summary!A4 -> Risk, Compliance & Responsible AI | B12: =Dimension_Summary!E4 -> 0 | C12: =Dimension_Summary!F4 -> 0 | D12: =Dimension_Summary!D4 -> 555 | E12: =IF(Dimension_Summary!F4="","",IF(Dimension_Summary!F4<=Config!B4,Config!B2,IF(Dimension_Summary!F4<=Config!B7,Config!B5,IF(Dimension_Summary!F4<=Config!B10,Config!B8,Config!B11)))) -> Emerging
A13: =Dimension_Summary!A5 -> Skills & Organizational Capability | B13: =Dimension_Summary!E5 -> 0 | C13: =Dimension_Summary!F5 -> 0 | D13: =Dimension_Summary!D5 -> 585 | E13: =IF(Dimension_Summary!F5="","",IF(Dimension_Summary!F5<=Config!B4,Config!B2,IF(Dimension_Summary!F5<=Config!B7,Config!B5,IF(Dimension_Summary!F5<=Config!B10,Config!B8,Config!B11)))) -> Emerging
A14: =Dimension_Summary!A6 -> Strategic & Leadership Readiness | B14: =Dimension_Summary!E6 -> 0 | C14: =Dimension_Summary!F6 -> 0 | D14: =Dimension_Summary!D6 -> 755 | E14: =IF(Dimension_Summary!F6="","",IF(Dimension_Summary!F6<=Config!B4,Config!B2,IF(Dimension_Summary!F6<=Config!B7,Config!B5,IF(Dimension_Summary!F6<=Config!B10,Config!B8,Config!B11)))) -> Emerging
A15: =Dimension_Summary!A7 -> Technology Infrastructure & Tooling | B15: =Dimension_Summary!E7 -> 0 | C15: =Dimension_Summary!F7 -> 0 | D15: =Dimension_Summary!D7 -> 815 | E15: =IF(Dimension_Summary!F7="","",IF(Dimension_Summary!F7<=Config!B4,Config!B2,IF(Dimension_Summary!F7<=Config!B7,Config!B5,IF(Dimension_Summary!F7<=Config!B10,Config!B8,Config!B11)))) -> Emerging
A16: =Dimension_Summary!A8 -> Use Case Maturity & Adoption | B16: =Dimension_Summary!E8 -> 0 | C16: =Dimension_Summary!F8 -> 0 | D16: =Dimension_Summary!D8 -> 540 | E16: =IF(Dimension_Summary!F8="","",IF(Dimension_Summary!F8<=Config!B4,Config!B2,IF(Dimension_Summary!F8<=Config!B7,Config!B5,IF(Dimension_Summary!F8<=Config!B10,Config!B8,Config!B11)))) -> Emerging
A18: GAP-ANALYSE — AFSTAND TOT STREEFNIVEAU (80%)
A19: Dimensie | B19: Huidige score (%) | C19: Streefwaarde (%) | D19: GAP (%) | E19: Prioriteit
A20: =Dimension_Summary!A2 -> Data Readiness | B20: =Dimension_Summary!F2 -> 0 | C20: 80% | D20: =IF(Dimension_Summary!F2="","",ROUND(80-Dimension_Summary!F2,1)) -> 80 | E20: =IF(Dimension_Summary!F2="","",IF(Dimension_Summary!F2>=80,"✓ Op niveau",IF(Dimension_Summary!F2>=60,"Laag",IF(Dimension_Summary!F2>=40,"Middel","Hoog")))) -> Hoog
A21: =Dimension_Summary!A3 -> Operations, Culture & Delivery | B21: =Dimension_Summary!F3 -> 0 | C21: 80% | D21: =IF(Dimension_Summary!F3="","",ROUND(80-Dimension_Summary!F3,1)) -> 80 | E21: =IF(Dimension_Summary!F3="","",IF(Dimension_Summary!F3>=80,"✓ Op niveau",IF(Dimension_Summary!F3>=60,"Laag",IF(Dimension_Summary!F3>=40,"Middel","Hoog")))) -> Hoog
A22: =Dimension_Summary!A4 -> Risk, Compliance & Responsible AI | B22: =Dimension_Summary!F4 -> 0 | C22: 80% | D22: =IF(Dimension_Summary!F4="","",ROUND(80-Dimension_Summary!F4,1)) -> 80 | E22: =IF(Dimension_Summary!F4="","",IF(Dimension_Summary!F4>=80,"✓ Op niveau",IF(Dimension_Summary!F4>=60,"Laag",IF(Dimension_Summary!F4>=40,"Middel","Hoog")))) -> Hoog
A23: =Dimension_Summary!A5 -> Skills & Organizational Capability | B23: =Dimension_Summary!F5 -> 0 | C23: 80% | D23: =IF(Dimension_Summary!F5="","",ROUND(80-Dimension_Summary!F5,1)) -> 80 | E23: =IF(Dimension_Summary!F5="","",IF(Dimension_Summary!F5>=80,"✓ Op niveau",IF(Dimension_Summary!F5>=60,"Laag",IF(Dimension_Summary!F5>=40,"Middel","Hoog")))) -> Hoog
A24: =Dimension_Summary!A6 -> Strategic & Leadership Readiness | B24: =Dimension_Summary!F6 -> 0 | C24: 80% | D24: =IF(Dimension_Summary!F6="","",ROUND(80-Dimension_Summary!F6,1)) -> 80 | E24: =IF(Dimension_Summary!F6="","",IF(Dimension_Summary!F6>=80,"✓ Op niveau",IF(Dimension_Summary!F6>=60,"Laag",IF(Dimension_Summary!F6>=40,"Middel","Hoog")))) -> Hoog
A25: =Dimension_Summary!A7 -> Technology Infrastructure & Tooling | B25: =Dimension_Summary!F7 -> 0 | C25: 80% | D25: =IF(Dimension_Summary!F7="","",ROUND(80-Dimension_Summary!F7,1)) -> 80 | E25: =IF(Dimension_Summary!F7="","",IF(Dimension_Summary!F7>=80,"✓ Op niveau",IF(Dimension_Summary!F7>=60,"Laag",IF(Dimension_Summary!F7>=40,"Middel","Hoog")))) -> Hoog
A26: =Dimension_Summary!A8 -> Use Case Maturity & Adoption | B26: =Dimension_Summary!F8 -> 0 | C26: 80% | D26: =IF(Dimension_Summary!F8="","",ROUND(80-Dimension_Summary!F8,1)) -> 80 | E26: =IF(Dimension_Summary!F8="","",IF(Dimension_Summary!F8>=80,"✓ Op niveau",IF(Dimension_Summary!F8>=60,"Laag",IF(Dimension_Summary!F8>=40,"Middel","Hoog")))) -> Hoog
A27: COMPLIANCE DEKKINGSGRAAD
A28: Framework | B28: Vragen gedekt | C28: Totaal vragen | D28: Dekking (%) | E28: Gem. score (0–5)
A29: EU AI Act | B29: =COUNTIFS(Sheet!$R$2:$R$266,"YES") -> 122 | C29: =Overall_Summary!B8 -> 265 | D29: =IF(C29=0,"",ROUND(B29/C29*100,1)) -> 46 | E29: =IF(COUNTIFS(Sheet!$R$2:$R$266,"YES",Sheet!$Q$2:$Q$266,"<>")=0,"",ROUND(AVERAGEIFS(Sheet!$Q$2:$Q$266,Sheet!$R$2:$R$266,"YES",Sheet!$Q$2:$Q$266,"<>"),2)) -> #DIV/0!
A30: NIST AI RMF | B30: =COUNTIFS(Sheet!$S$2:$S$266,"YES") -> 201 | C30: =Overall_Summary!B8 -> 265 | D30: =IF(C30=0,"",ROUND(B30/C30*100,1)) -> 75.8 | E30: =IF(COUNTIFS(Sheet!$S$2:$S$266,"YES",Sheet!$Q$2:$Q$266,"<>")=0,"",ROUND(AVERAGEIFS(Sheet!$Q$2:$Q$266,Sheet!$S$2:$S$266,"YES",Sheet!$Q$2:$Q$266,"<>"),2)) -> #DIV/0!
A31: ISO 42001 | B31: =COUNTIFS(Sheet!$T$2:$T$266,"YES") -> 202 | C31: =Overall_Summary!B8 -> 265 | D31: =IF(C31=0,"",ROUND(B31/C31*100,1)) -> 76.2 | E31: =IF(COUNTIFS(Sheet!$T$2:$T$266,"YES",Sheet!$Q$2:$Q$266,"<>")=0,"",ROUND(AVERAGEIFS(Sheet!$Q$2:$Q$266,Sheet!$T$2:$T$266,"YES",Sheet!$Q$2:$Q$266,"<>"),2)) -> #DIV/0!
A32: AI TRiSM | B32: =COUNTIFS(Sheet!$U$2:$U$266,"YES") -> 97 | C32: =Overall_Summary!B8 -> 265 | D32: =IF(C32=0,"",ROUND(B32/C32*100,1)) -> 36.6 | E32: =IF(COUNTIFS(Sheet!$U$2:$U$266,"YES",Sheet!$Q$2:$Q$266,"<>")=0,"",ROUND(AVERAGEIFS(Sheet!$Q$2:$Q$266,Sheet!$U$2:$U$266,"YES",Sheet!$Q$2:$Q$266,"<>"),2)) -> #DIV/0!
A33: Vertrouwelijk — Straightable Innovatie & Strategie — Automatisch berekend op basis van ingevulde antwoorden
